[{"week": "2019-09-05", "rank": 0, "song": "Se\u00f1orita", "artist": "Shawn Mendes, Camila Cabello", "streams": "45,594,172", "peak": "1", "previous": "1", "streak": "11", "release_date": "Jun 19, 2019", "first_entry": "Jun 27, 2019", "first_entry_pos": "1", "total_weeks": "11", "producers": "WATT, benny blanco", "songwriters": "Ali Tamposi, Benjamin Levin, Charlotte Aitchison, Jack Patterson, Andrew Wotman, Camila Cabello, Magnus H\u00f8iberg, Shawn Mendes", "source": "Island Records"}, {"week": "2019-09-05", "rank": 1, "song": "Circles", "artist": "Post Malone", "streams": "32,068,232", "peak": "2", "previous": "\u2014", "streak": "1", "release_date": "Sep 6, 2019", "first_entry": "Sep 5, 2019", "first_entry_pos": "2", "total_weeks": "1", "producers": "Post Malone, Frank Dukes, Louis Bell", "songwriters": "Adam Feeney, Allen Ritter, Billy Walsh, Boi-1da, Louis Bell, Austin Post, Kaan Gunesberk", "source": "Republic Records"}, {"week": "2019-09-05", "rank": 2, "song": "China", "artist": "Anuel AA, Daddy Yankee, KAROL G, J Balvin, Ozuna", "streams": "27,415,668", "peak": "2", "previous": "3", "streak": "7", "release_date": "Jul 19, 2019", "first_entry": "Jul 25, 2019", "first_entry_pos": "8", "total_weeks": "7", "producers": "Tainy", "songwriters": "Gaby Music, Tainy, Emmanuel Gazmey", "source": "2019 Real Hasta La Muerte, LLC."}, {"week": "2019-09-05", "rank": 3, "song": "Ransom", "artist": "Lil Tecca", "streams": "26,190,121", "peak": "3", "previous": "4", "streak": "14", "release_date": "Aug 30, 2019", "first_entry": "Jun 6, 2019", "first_entry_pos": "147", "total_weeks": "14", "producers": "Nick Mira, Taz Taylor", "songwriters": "Taz Taylor, Nick Mira, Tyler-Justin Anthony Sharpe", "source": "Republic Records"}, {"week": "2019-09-05", "rank": 4, "song": "Goodbyes (feat. Young Thug)", "artist": "Post Malone, Young Thug", "streams": "23,445,442", "peak": "2", "previous": "5", "streak": "9", "release_date": "Sep 6, 2019", "first_entry": "Jul 11, 2019", "first_entry_pos": "2", "total_weeks": "9", "producers": "Brian Lee, Louis Bell", "songwriters": "Billy Walsh, Brian Lee, Jeffery Williams, Jessie Lauren Foutz, Louis Bell, Austin Post, Val Blavatnik", "source": "Republic Records"}, {"week": "2019-09-05", "rank": 5, "song": "Dance Monkey", "artist": "Tones And I", "streams": "23,168,535", "peak": "6", "previous": "14", "streak": "7", "release_date": "Jul 16, 2021", "first_entry": "Jul 25, 2019", "first_entry_pos": "99", "total_weeks": "7", "producers": "Konstantin Kersting", "songwriters": "Toni Watson", "source": "Elektra (NEK)"}, {"week": "2019-09-05", "rank": 6, "song": "Beautiful People (feat. Khalid)", "artist": "Ed Sheeran, Khalid", "streams": "23,068,726", "peak": "3", "previous": "6", "streak": "10", "release_date": "Jul 12, 2019", "first_entry": "Jul 4, 2019", "first_entry_pos": "4", "total_weeks": "10", "producers": "Ed Sheeran, FRED, Max Martin, Shellback", "songwriters": "Max Martin, Ed Sheeran, Fred Gibson, Khalid Robinson, Shellback", "source": "Atlantic Records UK"}, {"week": "2019-09-05", "rank": 7, "song": "bad guy", "artist": "Billie Eilish", "streams": "21,245,918", "peak": "1", "previous": "8", "streak": "23", "release_date": "Mar 29, 2019", "first_entry": "Apr 4, 2019", "first_entry_pos": "1", "total_weeks": "23", "producers": "Finneas O'Connell", "songwriters": "Finneas O'Connell, Billie Eilish O'Connell", "source": "Darkroom/Interscope Records"}, {"week": "2019-09-05", "rank": 8, "song": "I Don't Care (with Justin Bieber)", "artist": "Ed Sheeran & Justin Bieber, Justin Bieber", "streams": "20,651,749", "peak": "1", "previous": "9", "streak": "17", "release_date": "Jul 12, 2019", "first_entry": "May 16, 2019", "first_entry_pos": "1", "total_weeks": "17", "producers": "FRED, Max Martin, Shellback", "songwriters": "Max Martin, Ed Sheeran, Fred Gibson, Jason Boyd, Justin Bieber, Shellback", "source": "Atlantic Records UK"}, {"week": "2019-09-05", "rank": 9, "song": "Someone You Loved", "artist": "Lewis Capaldi", "streams": "20,225,733", "peak": "7", "previous": "12", "streak": "35", "release_date": "May 17, 2019", "first_entry": "Jan 10, 2019", "first_entry_pos": "194", "total_weeks": "35", "producers": "TMS", "songwriters": "Benjamin Kohn, Peter Kelleher, Sam Roman, Tom Barnes, Lewis Capaldi", "source": "Vertigo Berlin"}, {"week": "2019-09-05", "rank": 10, "song": "How Do You Sleep?", "artist": "Sam Smith", "streams": "20,069,355", "peak": "7", "previous": "10", "streak": "7", "release_date": "Jul 19, 2019", "first_entry": "Jul 25, 2019", "first_entry_pos": "9", "total_weeks": "7", "producers": "Ilya Salmanzadeh", "songwriters": "Ilya Salmanzadeh, Max Martin, Savan Kotecha, Sam Smith", "source": "PLG - Capitol"}, {"week": "2019-09-05", "rank": 11, "song": "Lalala", "artist": "Y2K, bbno$", "streams": "19,933,879", "peak": "12", "previous": "19", "streak": "11", "release_date": "Jun 28, 2019", "first_entry": "Jun 27, 2019", "first_entry_pos": "74", "total_weeks": "11", "producers": "Y2K", "songwriters": "Alex Gumuchian, Ari Starace", "source": "Columbia"}, {"week": "2019-09-05", "rank": 12, "song": "Lover", "artist": "Taylor Swift", "streams": "19,793,619", "peak": "2", "previous": "2", "streak": "3", "release_date": "Aug 23, 2019", "first_entry": "Aug 22, 2019", "first_entry_pos": "13", "total_weeks": "3", "producers": "Jack Antonoff, Taylor Swift", "songwriters": "Taylor Swift", "source": "Taylor Swift"}, {"week": "2019-09-05", "rank": 13, "song": "Loco Contigo (feat. J. Balvin & Tyga)", "artist": "DJ Snake, J Balvin, Tyga", "streams": "18,894,886", "peak": "10", "previous": "11", "streak": "12", "release_date": "Jul 25, 2019", "first_entry": "Jun 20, 2019", "first_entry_pos": "51", "total_weeks": "12", "producers": "DJ Snake", "songwriters": "SECH, Jes\u00fas M. Nieves Cortez, Jos\u00e9 \u00c1lvaro Osorio Balv\u00edn, Justin Quiles, Michael Ray Stevenson, William Grigahcine", "source": "DJ Snake Music Productions Limited"}, {"week": "2019-09-05", "rank": 14, "song": "Old Town Road (feat. Billy Ray Cyrus) - Remix", "artist": "Lil Nas X, Billy Ray Cyrus", "streams": "18,031,493", "peak": "2", "previous": "13", "streak": "22", "release_date": "Jun 21, 2019", "first_entry": "Apr 11, 2019", "first_entry_pos": "2", "total_weeks": "22", "producers": "Atticus Matthew Ross, Youngkio, Michael Trent Reznor", "songwriters": "Jocelyn Donald, Atticus Matthew Ross, Billy Ray Cyrus, Kiowa Roukema, Michael Trent Reznor, Montero Lamar Hill", "source": "Columbia"}, {"week": "2019-09-05", "rank": 15, "song": "Callaita", "artist": "Bad Bunny, Tainy", "streams": "17,361,216", "peak": "7", "previous": "18", "streak": "14", "release_date": "May 31, 2019", "first_entry": "Jun 6, 2019", "first_entry_pos": "21", "total_weeks": "14", "producers": "Tainy", "songwriters": "Tainy, Benito Martinez", "source": "Rimas Entertainment LLC"}, {"week": "2019-09-05", "rank": 16, "song": "boyfriend (with Social House)", "artist": "Ariana Grande, Social House", "streams": "17,294,780", "peak": "3", "previous": "15", "streak": "5", "release_date": "Aug 2, 2019", "first_entry": "Aug 8, 2019", "first_entry_pos": "3", "total_weeks": "5", "producers": "Edgar Barrera, Steven Franks, Tommy Brown", "songwriters": "Anthony M Jones, Ariana Grande, Edgar Barrera, Steven Franks, Charles Anderson, Michael Foster, Tommy Brown", "source": "Republic Records"}, {"week": "2019-09-05", "rank": 17, "song": "Truth Hurts", "artist": "Lizzo", "streams": "15,878,645", "peak": "16", "previous": "22", "streak": "19", "release_date": "Apr 19, 2019", "first_entry": "May 2, 2019", "first_entry_pos": "49", "total_weeks": "19", "producers": "Ricky Reed", "songwriters": "Eric Frederic, jesse saint john, Amina Patrice Bogle-Barriteau, Melissa Jefferson, Steven Cheung", "source": "Nice Life/Atlantic"}, {"week": "2019-09-05", "rank": 18, "song": "LA CANCI\u00d3N", "artist": "J Balvin, Bad Bunny", "streams": "15,448,688", "peak": "17", "previous": "21", "streak": "10", "release_date": "Jun 28, 2019", "first_entry": "Jul 4, 2019", "first_entry_pos": "20", "total_weeks": "10", "producers": "Jose Nicael Arroyo", "songwriters": "Jose Nicael Arroyo, Tainy, Alejandro Ramirez, Bad Bunny, Gilbert Rodriguez Marte, J Balvin", "source": "Universal Music Latino / Rimas"}, {"week": "2019-09-05", "rank": 19, "song": "Yo x Ti, Tu x Mi", "artist": "ROSAL\u00cdA, Ozuna", "streams": "15,070,652", "peak": "20", "previous": "29", "streak": "3", "release_date": "Aug 15, 2019", "first_entry": "Aug 22, 2019", "first_entry_pos": "26", "total_weeks": "3", "producers": "El Guincho, Frank Dukes, ROSAL\u00cdA", "songwriters": "Ging FKA Frank Dukes, Jan Carlos Ozuna, Pablo Diaz-Reixa, Rosalia Vila Tobella", "source": "Columbia"}, {"week": "2019-09-05", "rank": 20, "song": "Sunflower - Spider-Man: Into the Spider-Verse", "artist": "Post Malone, Swae Lee", "streams": "14,695,973", "peak": "1", "previous": "25", "streak": "46", "release_date": "Dec 14, 2018", "first_entry": "Oct 25, 2018", "first_entry_pos": "5", "total_weeks": "46", "producers": "Louis Bell, Carter Lang", "songwriters": "Carter Lang, Louis Russel Bell, William Walsh, Austin Post, Carl Rosen, Khalif Malik Ibn Shaman Brown", "source": "Universal Records"}, {"week": "2019-09-05", "rank": 21, "song": "No Me Conoce - Remix", "artist": "JHAYCO, J Balvin, Bad Bunny", "streams": "14,518,434", "peak": "20", "previous": "23", "streak": "15", "release_date": "May 24, 2019", "first_entry": "May 30, 2019", "first_entry_pos": "115", "total_weeks": "15", "producers": "MVSIS", "songwriters": "De La Cruz, Benito Alberto Mart\u00ednez De La Garza, Jes\u00fas M. Nieves Cortez, Jos\u00e9 \u00c1lvaro Osorio Balv\u00edn, Michael Masis, Misael de la Cruz Reynoso PKA \u201cMDLC, Nydia Yera", "source": "N&E Entertainment LLC"}, {"week": "2019-09-05", "rank": 22, "song": "No Guidance (feat. Drake)", "artist": "Chris Brown, Drake", "streams": "13,847,431", "peak": "11", "previous": "28", "streak": "13", "release_date": "Jun 28, 2019", "first_entry": "Jun 13, 2019", "first_entry_pos": "21", "total_weeks": "13", "producers": "Vinylz, J-Louis, Noah \"40\" Shebib, Teddy Walton", "songwriters": "ANDERSON HERNANDEZ, Matthew Samuels, Nija Charles, Teddy Walton, A. Graham, Chris Brown, Joshua Huizar, Michee Patrick Lebrun, Noah \"40\" Shebib, Tyler James Bryant", "source": "Chris Brown Entertainment/RCA Records"}, {"week": "2019-09-05", "rank": 23, "song": "Otro Trago - Remix", "artist": "Sech, Ozuna, Anuel AA, Darell, Nicky Jam", "streams": "13,741,465", "peak": "11", "previous": "24", "streak": "6", "release_date": "Jul 26, 2019", "first_entry": "Aug 1, 2019", "first_entry_pos": "11", "total_weeks": "6", "producers": "D\u00edmelo Flow", "songwriters": "Carlos Isaias Morales Williams, Darell Castro, Emmanuel Gazmey Santiago, Juan Carlos Ozuna Rosado, Nick Rivera Caminero", "source": "Rich Music"}, {"week": "2019-09-05", "rank": 24, "song": "You Need To Calm Down", "artist": "Taylor Swift", "streams": "13,446,463", "peak": "4", "previous": "17", "streak": "12", "release_date": "Aug 23, 2019", "first_entry": "Jun 20, 2019", "first_entry_pos": "4", "total_weeks": "12", "producers": "Joel Little, Taylor Swift", "songwriters": "Joel Little, Taylor Swift", "source": "Taylor Swift"}, {"week": "2019-09-05", "rank": 25, "song": "The Man", "artist": "Taylor Swift", "streams": "13,170,044", "peak": "7", "previous": "7", "streak": "2", "release_date": "Aug 23, 2019", "first_entry": "Aug 29, 2019", "first_entry_pos": "7", "total_weeks": "2", "producers": "Joel Little, Taylor Swift", "songwriters": "Joel Little, Taylor Swift", "source": "Taylor Swift"}, {"week": "2019-09-05", "rank": 26, "song": "Money In The Grave (Drake ft. Rick Ross)", "artist": "Drake, Rick Ross", "streams": "13,010,929", "peak": "5", "previous": "27", "streak": "12", "release_date": "Jun 15, 2019", "first_entry": "Jun 20, 2019", "first_entry_pos": "6", "total_weeks": "12", "producers": "Cydney Christine, Ljay Currie, Asoteric, Delorean Black", "songwriters": "A. Graham, Cydney Christine Dade, Delorean Black, Joergensen, L. Currie, W. Roberts", "source": "Republic Records"}, {"week": "2019-09-05", "rank": 27, "song": "Tutu", "artist": "Camilo, Pedro Cap\u00f3", "streams": "12,809,212", "peak": "28", "previous": "43", "streak": "4", "release_date": "Aug 9, 2019", "first_entry": "Aug 15, 2019", "first_entry_pos": "49", "total_weeks": "4", "producers": "Richi Lopez, Jon Leone", "songwriters": "Jon Leone, Camilo Echeverry \"Camilo\", Richi Lopez", "source": "Sony Music Latin"}, {"week": "2019-09-05", "rank": 28, "song": "Piece Of Your Heart", "artist": "MEDUZA, Goodboys", "streams": "12,541,352", "peak": "14", "previous": "32", "streak": "21", "release_date": "Feb 1, 2019", "first_entry": "Apr 18, 2019", "first_entry_pos": "175", "total_weeks": "21", "producers": "Mattia Vitale, Simone Giani, Luca De Gregorio", "songwriters": "Conor Blake, Joshua Grimmett, Luca De Gregorio, Mattia Vitale, Nathan Cross, Simone Giani", "source": "Virgin"}, {"week": "2019-09-05", "rank": 29, "song": "fuck, i'm lonely", "artist": "Lauv, Anne-Marie", "streams": "12,502,607", "peak": "30", "previous": "41", "streak": "5", "release_date": "Mar 6, 2020", "first_entry": "Aug 8, 2019", "first_entry_pos": "39", "total_weeks": "5", "producers": "Lauv", "songwriters": "Ari Leff, Michael Matosic, Michael Pollack", "source": "Lauv"}, {"week": "2019-09-05", "rank": 30, "song": "Soltera (Remix)", "artist": "Lunay, Daddy Yankee, Bad Bunny", "streams": "12,372,635", "peak": "8", "previous": "34", "streak": "17", "release_date": "Oct 25, 2019", "first_entry": "May 16, 2019", "first_entry_pos": "15", "total_weeks": "17", "producers": "The Paradise, Jorge Echevarr\u00eda, Juan G. Rivera", "songwriters": "Chris Jedi, Gaby Music, Benito Martinez, Dulce como Candy, Jefnier Osorio Moreno, Luis E. Ortiz, Nino, Nino Karlo Segarra, Ram\u00f3n Luis Ayala Rodriguez", "source": "round2media - LaFamilia"}, {"week": "2019-09-05", "rank": 31, "song": "It's You", "artist": "Ali Gatie", "streams": "11,475,287", "peak": "27", "previous": "40", "streak": "12", "release_date": "Nov 8, 2019", "first_entry": "Jun 20, 2019", "first_entry_pos": "80", "total_weeks": "12", "producers": "Adriano, Happy Perez, \"Pop\" Wansel, Sam Wish", "songwriters": "Adrian Allahverdi, Nathan Perez, Ali Gatie, Andrew Wansel, Nicholas Adam Schiavone, Samuel Wishkoski", "source": "Warner Records"}, {"week": "2019-09-05", "rank": 32, "song": "Panini", "artist": "Lil Nas X", "streams": "11,334,032", "peak": "7", "previous": "39", "streak": "11", "release_date": "Jun 21, 2019", "first_entry": "Jun 27, 2019", "first_entry_pos": "7", "total_weeks": "11", "producers": "Take A Daytrip, Dot Da Genius", "songwriters": "David Biral, Denzel Baptiste, Oladipo Omishore, Kurt Cobain, Montero Lamar Hill", "source": "Columbia"}, {"week": "2019-09-05", "rank": 33, "song": "Takeaway", "artist": "The Chainsmokers, ILLENIUM, Lennon Stella", "streams": "11,302,380", "peak": "28", "previous": "38", "streak": "6", "release_date": "Dec 6, 2019", "first_entry": "Aug 1, 2019", "first_entry_pos": "30", "total_weeks": "6", "producers": "The Chainsmokers, ILLENIUM", "songwriters": "Christoph Bauss, Fridolin Walcher, Sam John Gray, Sorana Pacurar, Alex Pall, Andrew Taggart, Jonas Becker, Nicholas Miller, Timofei Crudu", "source": "Disruptor Records/Columbia"}, {"week": "2019-09-05", "rank": 34, "song": "The London (feat. J. Cole & Travis Scott)", "artist": "Young Thug, J. Cole, Travis Scott", "streams": "11,248,192", "peak": "6", "previous": "46", "streak": "15", "release_date": "Aug 16, 2019", "first_entry": "May 30, 2019", "first_entry_pos": "6", "total_weeks": "15", "producers": "", "songwriters": "Jeffery Williams, Tyler Williams, Jacques Webster II, Jermaine Cole", "source": "300 Entertainment/Atl"}, {"week": "2019-09-05", "rank": 35, "song": "Slide Away", "artist": "Miley Cyrus", "streams": "11,100,827", "peak": "31", "previous": "48", "streak": "3", "release_date": "May 31, 2019", "first_entry": "Aug 22, 2019", "first_entry_pos": "31", "total_weeks": "3", "producers": "Andrew Wyatt, Mike WiLL Made-It", "songwriters": "Andrew Wyatt, Michael L Williams II, Alma Miettinen, Miley Cyrus", "source": "RCA/Legacy"}, {"week": "2019-09-05", "rank": 36, "song": "Higher Love", "artist": "Kygo, Whitney Houston", "streams": "11,095,444", "peak": "31", "previous": "44", "streak": "10", "release_date": "Jun 28, 2019", "first_entry": "Jul 4, 2019", "first_entry_pos": "31", "total_weeks": "10", "producers": "Narada Michael Walden, Kyrre G\u00f8rvell-Dahll", "songwriters": "Steve Winwood, Will Jennings", "source": "Kygo/RCA Records"}, {"week": "2019-09-05", "rank": 37, "song": "QUE PRETENDES", "artist": "J Balvin, Bad Bunny", "streams": "10,893,037", "peak": "15", "previous": "45", "streak": "10", "release_date": "Jun 28, 2019", "first_entry": "Jul 4, 2019", "first_entry_pos": "15", "total_weeks": "10", "producers": "Sky Rompiendo", "songwriters": "Alejandro Ram\u00edrez Su\u00e1rez, Benito Antonio Mart\u00ednez Ocasio, Daniel Esteban Taborda Valencia, Jos\u00e9 \u00c1lvaro Osorio Balv\u00edn", "source": "Universal Music Latino / Rimas"}, {"week": "2019-09-05", "rank": 38, "song": "Adicto (with Anuel AA & Ozuna)", "artist": "Tainy, Anuel AA, Ozuna", "streams": "10,872,030", "peak": "39", "previous": "55", "streak": "2", "release_date": "Aug 22, 2019", "first_entry": "Aug 29, 2019", "first_entry_pos": "55", "total_weeks": "2", "producers": "Tainy", "songwriters": "Marco Masis, Emmanuel Gazmey Santiago, Jes\u00fas M. Nieves Cortez, Juan Carlos Ozuna Rosado", "source": "NEON16/Interscope Records"}, {"week": "2019-09-05", "rank": 39, "song": "11 PM", "artist": "Maluma", "streams": "10,601,047", "peak": "31", "previous": "47", "streak": "16", "release_date": "May 17, 2019", "first_entry": "May 23, 2019", "first_entry_pos": "72", "total_weeks": "16", "producers": "\u00c9dgar Barrera \"Edge\", Johany Correa \"Nyal\", Pedro Juan de la Ossa Medrano \"Gangsta\"", "songwriters": "Edgar Barrera, SECH, Vibarco, Carlos Isa\u00edas Morales, Johany Alejandro Correa, Juan Luis Londo\u00f1o, Luis Miguel Pardo Villa, Pedro Juan De La Ossa, Vicente Barco", "source": "Sony Music Latin"}, {"week": "2019-09-05", "rank": 40, "song": "Cruel Summer", "artist": "Taylor Swift", "streams": "10,366,416", "peak": "16", "previous": "16", "streak": "2", "release_date": "Aug 23, 2019", "first_entry": "Aug 29, 2019", "first_entry_pos": "16", "total_weeks": "2", "producers": "Jack Antonoff, Taylor Swift", "songwriters": "Annie Clark, Jack Antonoff, Taylor Swift", "source": "Taylor Swift"}, {"week": "2019-09-05", "rank": 41, "song": "Motivation", "artist": "Normani", "streams": "10,353,406", "peak": "42", "previous": "56", "streak": "3", "release_date": "Aug 16, 2019", "first_entry": "Aug 22, 2019", "first_entry_pos": "42", "total_weeks": "3", "producers": "ILYA", "songwriters": "Ariana Grande, Ilya Salmanzadeh, Max Martin, Savan Kotecha, Normani Kordei Hamilton, Sh\u00e9yaa Bin Abraham-Joseph", "source": "Keep Cool/RCA Records"}, {"week": "2019-09-05", "rank": 42, "song": "7 rings", "artist": "Ariana Grande", "streams": "9,881,434", "peak": "1", "previous": "49", "streak": "33", "release_date": "Feb 8, 2019", "first_entry": "Jan 24, 2019", "first_entry_pos": "1", "total_weeks": "33", "producers": "Tommy Brown, Charles Anderson, Michael Foster", "songwriters": "Ariana Grande, Kimberly Krysiuk, Oscar Hammerstein II, Richard Rogers, Tayla Parx, Tommy Brown, Victoria Mon\u00e9t, Charles Anderson, Michael Foster, Njomza Vitia", "source": "Republic Records"}, {"week": "2019-09-05", "rank": 43, "song": "Con Altura", "artist": "ROSAL\u00cdA, J Balvin, El Guincho", "streams": "9,874,934", "peak": "30", "previous": "51", "streak": "23", "release_date": "Mar 28, 2019", "first_entry": "Apr 4, 2019", "first_entry_pos": "41", "total_weeks": "23", "producers": "El Guincho, Frank Dukes, ROSAL\u00cdA", "songwriters": "Frank Dukes, Pablo Diaz-Reixa, Rosalia Vila Tobella, Teo Halm, Alejandro Ramirez, Jos\u00e9 \u00c1lvaro Osorio Balv\u00edn, Mariachi Budda", "source": "Columbia"}, {"week": "2019-09-05", "rank": 44, "song": "Good as Hell", "artist": "Lizzo", "streams": "9,828,231", "peak": "45", "previous": "64", "streak": "9", "release_date": "Mar 9, 2016", "first_entry": "Jul 11, 2019", "first_entry_pos": "153", "total_weeks": "9", "producers": "Ricky Reed", "songwriters": "Eric Frederic, Melissa Jefferson", "source": "Nice Life/Atlantic"}, {"week": "2019-09-05", "rank": 45, "song": "Teeth", "artist": "5 Seconds of Summer", "streams": "9,555,911", "peak": "46", "previous": "62", "streak": "2", "release_date": "Aug 23, 2019", "first_entry": "Aug 29, 2019", "first_entry_pos": "62", "total_weeks": "2", "producers": "Andrew Watt, Louis Bell", "songwriters": "Ali Tamposi, Andrew Wotman, Louis Bell, Ryan Tedder, Ashton Irwin, Bernard Sumner, Carl Sturken, Evan Rogers, Gillian Lesley Gilbert, Luke Hemmings, Peter Hook, Stephen Morris", "source": "UMGRI Interscope"}, {"week": "2019-09-05", "rank": 46, "song": "Shallow", "artist": "Lady Gaga, Bradley Cooper", "streams": "9,515,682", "peak": "3", "previous": "54", "streak": "49", "release_date": "Oct 5, 2018", "first_entry": "Oct 4, 2018", "first_entry_pos": "69", "total_weeks": "49", "producers": "Lady Gaga, Benjamin Rice", "songwriters": "Andrew Wyatt, Mark Ronson, Anthony Rossomando, Lady Gaga", "source": "A Star is Born OST"}, {"week": "2019-09-05", "rank": 47, "song": "Sucker", "artist": "Jonas Brothers", "streams": "9,048,107", "peak": "2", "previous": "59", "streak": "27", "release_date": "Jun 7, 2019", "first_entry": "Mar 7, 2019", "first_entry_pos": "2", "total_weeks": "27", "producers": "Ryan Tedder", "songwriters": "Frank Dukes, Louis Bell, Ryan Tedder, Homer Steinweiss, Joe Jonas, Kevin Jonas, Mustafa Ahmed, Nick Jonas", "source": "Jonas Brothers Recording"}, {"week": "2019-09-05", "rank": 48, "song": "ME! (feat. Brendon Urie of Panic! At The Disco)", "artist": "Taylor Swift, Brendon Urie, Panic! At The Disco", "streams": "9,027,590", "peak": "2", "previous": "33", "streak": "19", "release_date": "Aug 23, 2019", "first_entry": "May 2, 2019", "first_entry_pos": "2", "total_weeks": "19", "producers": "Joel Little, Taylor Swift", "songwriters": "Joel Little, Brendon Urie, Taylor Swift", "source": "Taylor Swift"}, {"week": "2019-09-05", "rank": 49, "song": "Con Calma", "artist": "Daddy Yankee, Snow", "streams": "9,013,549", "peak": "2", "previous": "53", "streak": "32", "release_date": "Jan 24, 2019", "first_entry": "Jan 31, 2019", "first_entry_pos": "80", "total_weeks": "32", "producers": "Play-N-Skillz, David \u201cScott Summers\u201d Macias", "songwriters": "Darrin O'Brien, Juan G. Rivera, Ram\u00f3n Luis Ayala Rodriguez", "source": "El Cartel Records (EC3)"}, {"week": "2019-09-05", "rank": 50, "song": "If I Can't Have You", "artist": "Shawn Mendes", "streams": "8,988,377", "peak": "4", "previous": "58", "streak": "18", "release_date": "Jun 19, 2019", "first_entry": "May 9, 2019", "first_entry_pos": "4", "total_weeks": "18", "producers": "Shawn Mendes, Teddy Geiger", "songwriters": "Scott Harris, Teddy Geiger, Nate Mercereau, Shawn Mendes", "source": "Island Records"}, {"week": "2019-09-05", "rank": 51, "song": "Norman fucking Rockwell", "artist": "Lana Del Rey", "streams": "8,937,691", "peak": "52", "previous": "\u2014", "streak": "1", "release_date": "Aug 30, 2019", "first_entry": "Sep 5, 2019", "first_entry_pos": "52", "total_weeks": "1", "producers": "Lana Del Rey, Jack Antonoff", "songwriters": "Jack Antonoff, Lana Del Rey", "source": "Polydor Records"}, {"week": "2019-09-05", "rank": 52, "song": "Babushka Boi", "artist": "A$AP Rocky", "streams": "8,903,408", "peak": "53", "previous": "\u2014", "streak": "1", "release_date": "Aug 28, 2019", "first_entry": "Sep 5, 2019", "first_entry_pos": "53", "total_weeks": "1", "producers": "H\u00e9ctor Delgado, Boys Noize", "songwriters": "Alexander Ridha, H\u00e9ctor Delgado, Mario Reddick, Rakim Mayers", "source": "A$AP Worldwide/Polo Grounds Music/RCA Records"}, {"week": "2019-09-05", "rank": 53, "song": "I.F.L.Y.", "artist": "Bazzi", "streams": "8,534,183", "peak": "47", "previous": "60", "streak": "7", "release_date": "Aug 9, 2019", "first_entry": "Jul 25, 2019", "first_entry_pos": "102", "total_weeks": "7", "producers": "Bazzi, Kevin White", "songwriters": "Bazzi", "source": "iamcosmic"}, {"week": "2019-09-05", "rank": 54, "song": "I Forgot That You Existed", "artist": "Taylor Swift", "streams": "8,441,132", "peak": "20", "previous": "20", "streak": "2", "release_date": "Aug 23, 2019", "first_entry": "Aug 29, 2019", "first_entry_pos": "20", "total_weeks": "2", "producers": "Louis Bell, Frank Dukes, Taylor Swift", "songwriters": "Adam Feeney, Louis Bell, Taylor Swift", "source": "Taylor Swift"}, {"week": "2019-09-05", "rank": 55, "song": "Happier", "artist": "Marshmello, Bastille", "streams": "8,423,767", "peak": "2", "previous": "66", "streak": "55", "release_date": "Aug 17, 2018", "first_entry": "Aug 23, 2018", "first_entry_pos": "32", "total_weeks": "55", "producers": "Marshmello", "songwriters": "Steve Mac, Dan Smith, Marshmello", "source": "Joytime Collective"}, {"week": "2019-09-05", "rank": 56, "song": "Talk (feat. Disclosure)", "artist": "Khalid, Disclosure", "streams": "8,191,402", "peak": "10", "previous": "61", "streak": "30", "release_date": "Apr 5, 2019", "first_entry": "Feb 14, 2019", "first_entry_pos": "25", "total_weeks": "30", "producers": "Disclosure", "songwriters": "Guy Lawrence, Howard Lawrence, Khalid Robinson", "source": "Right Hand Music Group, LLC/RCA Records"}, {"week": "2019-09-05", "rank": 57, "song": "SICKO MODE", "artist": "Travis Scott", "streams": "8,169,845", "peak": "2", "previous": "112", "streak": "57", "release_date": "Aug 3, 2018", "first_entry": "Aug 9, 2018", "first_entry_pos": "2", "total_weeks": "57", "producers": "Hit-Boy, OZ, Tay Keith, Cubeatz, Rog\u00e9t Chahayed", "songwriters": "Brytavious Chambers, Harry Wayne Casey, Hit-Boy, Kevin Gomringer (of CuBeatz), Ozan Yildirim, Rog\u00e9t Chahayed, Tim Gomringer, A. Graham, Ali Shaheed Jones-Muhammad, Bryan Higgins, Chauncey Hollis, Christopher Martin, Christopher Wallace, Chylow Parker, Cydel Young, Fred Scruggs, JOHN EDWARD HAWKINS, Jacques Webster, James Jackson, Kamaal Fareed, Keith Elam, Khalif Brown, Kirk Jones, Luther Campbell, MIKE DEAN, Malik Taylor, Mirsad Dervic, Osten Harvey, Richard Finch, Trevor Smith, Tyrone Taylor", "source": "Cactus Jack / Epic"}, {"week": "2019-09-05", "rank": 58, "song": "lovely (with Khalid)", "artist": "Billie Eilish, Khalid", "streams": "8,158,963", "peak": "24", "previous": "68", "streak": "72", "release_date": "Apr 19, 2018", "first_entry": "Apr 26, 2018", "first_entry_pos": "138", "total_weeks": "72", "producers": "Finneas O'Connell", "songwriters": "Finneas O'Connell, Billie Eilish O'Connell, Khalid Robinson", "source": "Darkroom"}, {"week": "2019-09-05", "rank": 59, "song": "Wow.", "artist": "Post Malone", "streams": "8,033,506", "peak": "2", "previous": "74", "streak": "37", "release_date": "Sep 6, 2019", "first_entry": "Dec 27, 2018", "first_entry_pos": "25", "total_weeks": "37", "producers": "Louis Bell, Frank Dukes", "songwriters": "Adam Feeny, Billy Walsh, Louis Bell, Austin Post", "source": "Republic Records"}, {"week": "2019-09-05", "rank": 60, "song": "Doin' Time", "artist": "Lana Del Rey", "streams": "7,870,328", "peak": "61", "previous": "\u2014", "streak": "1", "release_date": "Aug 30, 2019", "first_entry": "May 23, 2019", "first_entry_pos": "119", "total_weeks": "2", "producers": "Andrew Watt, Happy Perez", "songwriters": "George Gershwin, Adam Keefe Horovitz, Adam Nathaniel Yauch, Bradley James Nowell, Dorothy Heyward, DuBose Heyward, Ira Gershwin, Marshall Raymond Goodman, Rick Rubin", "source": "Polydor Records"}, {"week": "2019-09-05", "rank": 61, "song": "when the party's over", "artist": "Billie Eilish", "streams": "7,707,299", "peak": "9", "previous": "77", "streak": "46", "release_date": "Mar 29, 2019", "first_entry": "Oct 25, 2018", "first_entry_pos": "18", "total_weeks": "46", "producers": "Finneas O'Connell", "songwriters": "Finneas O'Connell", "source": "Darkroom/Interscope Records"}, {"week": "2019-09-05", "rank": 62, "song": "One Thing Right", "artist": "Marshmello, Kane Brown", "streams": "7,648,469", "peak": "30", "previous": "72", "streak": "11", "release_date": "Jun 21, 2019", "first_entry": "Jun 27, 2019", "first_entry_pos": "36", "total_weeks": "11", "producers": "Marshmello", "songwriters": "Jesse Frasure, Matt McGinn, Josh Hoge, Kane Brown, Marshmello", "source": "Joytime Collective"}, {"week": "2019-09-05", "rank": 63, "song": "Hot Girl Summer (feat. Nicki Minaj & Ty Dolla $ign)", "artist": "Megan Thee Stallion, Ty Dolla $ign, Nicki Minaj", "streams": "7,623,186", "peak": "32", "previous": "71", "streak": "4", "release_date": "Aug 9, 2019", "first_entry": "Aug 15, 2019", "first_entry_pos": "32", "total_weeks": "4", "producers": "Bone Collector, Juicy J", "songwriters": "Derrick Milano, Earl On The Beat", "source": "300 Entertainment"}, {"week": "2019-09-05", "rank": 64, "song": "Did It Again", "artist": "Lil Tecca", "streams": "7,604,997", "peak": "65", "previous": "136", "streak": "3", "release_date": "Aug 30, 2019", "first_entry": "Aug 22, 2019", "first_entry_pos": "152", "total_weeks": "3", "producers": "Nick Mira, Taz Taylor, E-Trou", "songwriters": "Taz Taylor, Elias Latrou, Nick Mira, Tyler-Justin Anthony Sharpe", "source": "Republic Records"}, {"week": "2019-09-05", "rank": 65, "song": "Rescue Me", "artist": "OneRepublic", "streams": "7,585,578", "peak": "32", "previous": "81", "streak": "16", "release_date": "May 17, 2019", "first_entry": "May 23, 2019", "first_entry_pos": "65", "total_weeks": "16", "producers": "Brent Kutzle, Ryan Tedder, Tyler Spry", "songwriters": "Ryan Tedder, Brent Kutzle", "source": "Mosley Music/Interscope Records"}, {"week": "2019-09-05", "rank": 66, "song": "hot girl bummer", "artist": "blackbear", "streams": "7,468,452", "peak": "67", "previous": "160", "streak": "2", "release_date": "Aug 21, 2020", "first_entry": "Aug 29, 2019", "first_entry_pos": "160", "total_weeks": "2", "producers": "Andrew Goldstein, blackbear", "songwriters": "Andrew Goldstein, Matthew Musto", "source": "Alamo"}, {"week": "2019-09-05", "rank": 67, "song": "Si Se Da - Remix", "artist": "Myke Towers, Farruko, Arc\u00e1ngel, Sech, Zion", "streams": "7,445,621", "peak": "68", "previous": "75", "streak": "5", "release_date": "Aug 2, 2019", "first_entry": "Aug 8, 2019", "first_entry_pos": "119", "total_weeks": "5", "producers": "Montana the Producer", "songwriters": "Sech, Arc\u00e1ngel, Farruko, Jose Reyes, Myke Towers, Orlando Cepeda Matos, Zion", "source": "2019 Casablanca Records & One World Music | Distributed by GLAD Empire"}, {"week": "2019-09-05", "rank": 68, "song": "Otro Trago", "artist": "Sech, Darell", "streams": "7,437,240", "peak": "4", "previous": "69", "streak": "19", "release_date": "Apr 19, 2019", "first_entry": "May 2, 2019", "first_entry_pos": "90", "total_weeks": "19", "producers": "D\u00edmelo Flow", "songwriters": "Carlos Isaias Morales Williams, Jorge Valdes, Darell Castro, JOSHUA MENDEZ", "source": "Rich Music/Ingrooves Records"}, {"week": "2019-09-05", "rank": 69, "song": "bad guy (with Justin Bieber)", "artist": "Billie Eilish, Justin Bieber", "streams": "7,436,429", "peak": "9", "previous": "67", "streak": "8", "release_date": "Jul 11, 2019", "first_entry": "Jul 18, 2019", "first_entry_pos": "9", "total_weeks": "8", "producers": "Finneas O'Connell", "songwriters": "Billie Eilish O'Connell, Finneas O'Connell, Jason Boyd, Justin Bieber", "source": "Darkroom/Interscope Records"}, {"week": "2019-09-05", "rank": 70, "song": "Suge", "artist": "DaBaby", "streams": "7,415,460", "peak": "26", "previous": "83", "streak": "19", "release_date": "Mar 1, 2019", "first_entry": "May 2, 2019", "first_entry_pos": "157", "total_weeks": "19", "producers": "jetsonmade, Pooh Beatz", "songwriters": "Pooh Beatz, jetsonmade, DaBaby", "source": "South Coast Music Group/Interscope Records"}, {"week": "2019-09-05", "rank": 71, "song": "Verte Ir", "artist": "DJ Luian, Mambo Kingz, Anuel AA, Nicky Jam, Darell, Brytiago", "streams": "7,363,309", "peak": "25", "previous": "79", "streak": "23", "release_date": "Mar 28, 2019", "first_entry": "Apr 4, 2019", "first_entry_pos": "63", "total_weeks": "23", "producers": "Mambo Kingz", "songwriters": "Luian Malav\u00e9, Bryan Cancel, Edgar Semper, Eladio Carrion, Emanuel Gazmey, Hector Ramos, Kedin Maysonet, Nick Caminero, Osval Elias Castro, Xavier Semper", "source": "Hear This Music"}, {"week": "2019-09-05", "rank": 72, "song": "rockstar (feat. 21 Savage)", "artist": "Post Malone, 21 Savage", "streams": "7,314,501", "peak": "1", "previous": "88", "streak": "103", "release_date": "Apr 27, 2018", "first_entry": "Sep 21, 2017", "first_entry_pos": "1", "total_weeks": "103", "producers": "Louis Bell, Tank God", "songwriters": "Louis Bell, Austin Post, Carl Austin Rosen, Jo-Vaughn Virginie, Olufunmibi Awoshiley, Sh\u00e9yaa Bin Abraham-Joseph", "source": "Republic Records"}, {"week": "2019-09-05", "rank": 73, "song": "Never Really Over", "artist": "Katy Perry", "streams": "7,302,250", "peak": "10", "previous": "63", "streak": "14", "release_date": "May 31, 2019", "first_entry": "Jun 6, 2019", "first_entry_pos": "11", "total_weeks": "14", "producers": "Zedd, Dreamlab", "songwriters": "Hayley Warner, Jason Gill, Michelle Buzz, Anton Zaslavski, Dagny Norvoll Sandvik, Daniel James, Gino Barletta, Katy Perry, Leah Haywood", "source": "Capitol Records"}, {"week": "2019-09-05", "rank": 74, "song": "Bohemian Rhapsody - Remastered 2011", "artist": "Queen", "streams": "7,258,678", "peak": "11", "previous": "86", "streak": "47", "release_date": "Nov 21, 1975", "first_entry": "Jan 5, 2017", "first_entry_pos": "183", "total_weeks": "53", "producers": "Roy Thomas Baker, Queen", "songwriters": "Freddie Mercury", "source": "Hollywood Records"}, {"week": "2019-09-05", "rank": 75, "song": "Calma - Remix", "artist": "Pedro Cap\u00f3, Farruko", "streams": "7,250,648", "peak": "5", "previous": "78", "streak": "43", "release_date": "Oct 5, 2018", "first_entry": "Nov 15, 2018", "first_entry_pos": "168", "total_weeks": "43", "producers": "George Noriega, Rec808, Sharo Towers", "songwriters": "Carlos Efr\u00e9n Reyes Rosado a/k/a Farruko, Franklin Jovani Mart\u00ednez, Gabriel Edgar Gonzalez Perez, George Noriega, Marcos G. P\u00e9rez a/k/a Sharo Towers, Pedro Cap\u00f3", "source": "Sony Music Latin"}, {"week": "2019-09-05", "rank": 76, "song": "Dancing With A Stranger (with Normani)", "artist": "Sam Smith, Normani", "streams": "7,221,998", "peak": "7", "previous": "85", "streak": "34", "release_date": "Jan 11, 2019", "first_entry": "Jan 17, 2019", "first_entry_pos": "8", "total_weeks": "34", "producers": "Stargate, Jimmy Napes", "songwriters": "James Napier, Mikkel Storleer Eriksen, Tor Erik Hermansen, Normani Hamilton, Sam Smith", "source": "PLG - Capitol"}, {"week": "2019-09-05", "rank": 77, "song": "Post Malone (feat. RANI)", "artist": "Sam Feldt, RANI", "streams": "7,163,897", "peak": "59", "previous": "90", "streak": "11", "release_date": "Aug 16, 2019", "first_entry": "Jun 27, 2019", "first_entry_pos": "164", "total_weeks": "11", "producers": "", "songwriters": "Jonas Kr\u00f6per, Roxanne Emery, Dominic Lyttle, Sammy Renders, Shannon Hilversum", "source": "Spinnin' Remixes"}, {"week": "2019-09-05", "rank": 78, "song": "Fuck it I love you", "artist": "Lana Del Rey", "streams": "7,129,257", "peak": "79", "previous": "161", "streak": "2", "release_date": "Aug 30, 2019", "first_entry": "Aug 29, 2019", "first_entry_pos": "161", "total_weeks": "2", "producers": "Jack Antonoff, Andrew Watt, Louis Bell", "songwriters": "Andrew Wotman, Jack Antonoff, Louis Bell, Lana Del Rey", "source": "Polydor Records"}, {"week": "2019-09-05", "rank": 79, "song": "South of the Border (feat. Camila Cabello & Cardi B)", "artist": "Ed Sheeran, Camila Cabello, Cardi B", "streams": "7,090,201", "peak": "10", "previous": "84", "streak": "8", "release_date": "Jul 12, 2019", "first_entry": "Jul 18, 2019", "first_entry_pos": "10", "total_weeks": "8", "producers": "Ed Sheeran, FRED, Steve Mac", "songwriters": "Steve Mac, Belcalis Almanzar, Camila Cabello, Ed Sheeran, Fred Gibson, Jordan Thorpe", "source": "Atlantic Records UK"}, {"week": "2019-09-05", "rank": 80, "song": "Instagram", "artist": "Dimitri Vegas & Like Mike, David Guetta, Daddy Yankee, Afro Bros, NATTI NATASHA, Dimitri Vegas, Like Mike", "streams": "7,075,390", "peak": "81", "previous": "87", "streak": "9", "release_date": "Jul 5, 2019", "first_entry": "Jul 11, 2019", "first_entry_pos": "139", "total_weeks": "9", "producers": "Dimitri Vegas & Like Mike, David Guetta, Afro Bros", "songwriters": "Angemi, David Guetta, Dimitri Thivaios, Francesca Richard, Giordano M.S. Ashruf, Michael Thivaios, Natalia Alexandra Gutierrez Batista, Peter Hanna, Ram\u00f3n Luis Ayala Rodriguez, Rashid M.S. M Badloe, Sharef M.R. Badloe", "source": "Epic Amsterdam"}, {"week": "2019-09-05", "rank": 81, "song": "Love Me", "artist": "Lil Tecca", "streams": "7,070,233", "peak": "82", "previous": "106", "streak": "5", "release_date": "Aug 30, 2019", "first_entry": "Aug 8, 2019", "first_entry_pos": "170", "total_weeks": "5", "producers": "Dystinkt Beats", "songwriters": "Tomislav Ratesic, Tyler-Justin Anthony Sharpe", "source": "Republic Records"}, {"week": "2019-09-05", "rank": 82, "song": "Bad Bad Bad (feat. Lil Baby)", "artist": "Young Thug, Lil Baby", "streams": "7,048,294", "peak": "46", "previous": "76", "streak": "3", "release_date": "Aug 16, 2019", "first_entry": "Aug 22, 2019", "first_entry_pos": "46", "total_weeks": "3", "producers": "", "songwriters": "Wheezy Beats, Young Thug", "source": "300 Entertainment/Atl"}, {"week": "2019-09-05", "rank": 83, "song": "3 Nights", "artist": "Dominic Fike", "streams": "7,048,242", "peak": "51", "previous": "80", "streak": "21", "release_date": "Oct 16, 2018", "first_entry": "Jan 31, 2019", "first_entry_pos": "197", "total_weeks": "23", "producers": "Kevin \"Capi\" Carbo", "songwriters": "Dominic Fike, Kevin \"Capi\" Carbo", "source": "Columbia"}, {"week": "2019-09-05", "rank": 84, "song": "Paper Rings", "artist": "Taylor Swift", "streams": "7,045,896", "peak": "26", "previous": "26", "streak": "2", "release_date": "Aug 23, 2019", "first_entry": "Aug 29, 2019", "first_entry_pos": "26", "total_weeks": "2", "producers": "Jack Antonoff, Taylor Swift", "songwriters": "Jack Antonoff, Taylor Swift", "source": "Taylor Swift"}, {"week": "2019-09-05", "rank": 85, "song": "Without Me", "artist": "Halsey", "streams": "7,045,837", "peak": "4", "previous": "89", "streak": "48", "release_date": "Jan 17, 2020", "first_entry": "Oct 11, 2018", "first_entry_pos": "11", "total_weeks": "48", "producers": "Louis Bell", "songwriters": "Amy Allen, Delacey, Juice WRLD, Louis Bell, Scott Storch, Tim Mosley, Halsey, Justin Timberlake", "source": "Capitol Records"}, {"week": "2019-09-05", "rank": 86, "song": "Summer Days (feat. Macklemore & Patrick Stump of Fall Out Boy)", "artist": "Martin Garrix, Macklemore, Fall Out Boy", "streams": "7,040,047", "peak": "19", "previous": "70", "streak": "19", "release_date": "Apr 25, 2019", "first_entry": "May 2, 2019", "first_entry_pos": "118", "total_weeks": "19", "producers": "Martin Garrix", "songwriters": "Brian Lee, Jaramye Daniels, Ben Haggerty, Giorgio Tuinfort, Martijn Garritsen", "source": "Epic Amsterdam"}, {"week": "2019-09-05", "rank": 87, "song": "Old Town Road", "artist": "Lil Nas X", "streams": "7,029,228", "peak": "3", "previous": "82", "streak": "26", "release_date": "Jun 21, 2019", "first_entry": "Mar 14, 2019", "first_entry_pos": "99", "total_weeks": "26", "producers": "Youngkio, Michael Trent Reznor, Atticus Matthew Ross", "songwriters": "Atticus Matthew Ross, Kiowa Roukema, Michael Trent Reznor, Montero Lamar Hill", "source": "Columbia"}, {"week": "2019-09-05", "rank": 88, "song": "Ransom (with Juice WRLD) - Remix", "artist": "Lil Tecca, Juice WRLD", "streams": "6,973,264", "peak": "78", "previous": "104", "streak": "3", "release_date": "Aug 30, 2019", "first_entry": "Aug 22, 2019", "first_entry_pos": "78", "total_weeks": "3", "producers": "Nick Mira, Taz Taylor", "songwriters": "Jarad Higgins, Taz Taylor, Nick Mira, Tyler-Justin Anthony Sharpe", "source": "Republic Records"}, {"week": "2019-09-05", "rank": 89, "song": "Better Now", "artist": "Post Malone", "streams": "6,935,016", "peak": "1", "previous": "102", "streak": "71", "release_date": "Apr 27, 2018", "first_entry": "May 3, 2018", "first_entry_pos": "1", "total_weeks": "71", "producers": "Frank Dukes, Louis Bell", "songwriters": "Adam Feeney, Louis Bell, William Walsh, Austin Post, Carl Rosen, Kaan Gunesberk", "source": "Republic Records"}, {"week": "2019-09-05", "rank": 90, "song": "Graduation (with Juice WRLD)", "artist": "benny blanco, Juice WRLD", "streams": "6,927,146", "peak": "91", "previous": "\u2014", "streak": "1", "release_date": "Aug 30, 2019", "first_entry": "Sep 5, 2019", "first_entry_pos": "91", "total_weeks": "1", "producers": "benny blanco, Happy Perez, Cashmere Cat", "songwriters": "Benjamin Levin, Jarad Higgins, Nathan Perez, Colleen Fitzpatrick, Josh Deutsch, Magnus H\u00f8iberg", "source": "Friends Keep Secrets, under exclusive license to Interscope Records"}, {"week": "2019-09-05", "rank": 91, "song": "Eastside (with Halsey & Khalid)", "artist": "benny blanco, Halsey, Khalid", "streams": "6,816,297", "peak": "4", "previous": "100", "streak": "60", "release_date": "Dec 7, 2018", "first_entry": "Jul 19, 2018", "first_entry_pos": "34", "total_weeks": "60", "producers": "WATT, benny blanco, Cashmere Cat", "songwriters": "Nathan Perez, benny blanco, Ed Sheeran, Halsey, Khalid Robinson", "source": "Friends Keep Secrets/Interscope Records"}, {"week": "2019-09-05", "rank": 92, "song": "Sweet but Psycho", "artist": "Ava Max", "streams": "6,721,075", "peak": "6", "previous": "98", "streak": "49", "release_date": "Sep 18, 2020", "first_entry": "Oct 4, 2018", "first_entry_pos": "115", "total_weeks": "49", "producers": "Cirkut", "songwriters": "Henry Walter, Madison Love, Amanda Ava Koci, Andreas Andersen Haukeland, William Lobban-Bean", "source": "Atlantic Records"}, {"week": "2019-09-05", "rank": 93, "song": "Baby (Lil Baby feat. DaBaby)", "artist": "Quality Control, Lil Baby, DaBaby", "streams": "6,688,369", "peak": "67", "previous": "94", "streak": "7", "release_date": "Aug 16, 2019", "first_entry": "Jul 25, 2019", "first_entry_pos": "120", "total_weeks": "7", "producers": "Wheezy", "songwriters": "Wesley Glass, Dominique Jones, JONATHAN LYNDALE Kirk", "source": "Quality Control Music/Motown Records"}, {"week": "2019-09-05", "rank": 94, "song": "thank u, next", "artist": "Ariana Grande", "streams": "6,672,556", "peak": "1", "previous": "96", "streak": "44", "release_date": "Feb 8, 2019", "first_entry": "Nov 8, 2018", "first_entry_pos": "1", "total_weeks": "44", "producers": "Tommy Brown, Michael Foster, Charles Anderson", "songwriters": "Ariana Grande, Kimberly Krysiuk, Tayla Parx, Tommy Brown, Victoria McCants, Charles Anderson, Michael Foster, Njomza Vitia", "source": "Republic Records"}, {"week": "2019-09-05", "rank": 95, "song": "Te Robar\u00e9", "artist": "Nicky Jam, Ozuna", "streams": "6,594,191", "peak": "28", "previous": "91", "streak": "24", "release_date": "Nov 1, 2019", "first_entry": "Mar 28, 2019", "first_entry_pos": "75", "total_weeks": "24", "producers": "Chris Jedi, Gaby Music", "songwriters": "Carlos E. Ortiz, Juan G. Rivera, Ozuna, Jan Carlos Ozuna \"Ozuna\", Johnatan Ballesteros, Jose E. Ortiz Rivera, Juan Diego Medina, Nick Rivera Caminero, Nick Rivera Caminero \"Nicky Jam\", Nino Karlo Segarra, Vicente Saavedra", "source": "Sony Music Latin"}, {"week": "2019-09-05", "rank": 96, "song": "Believer", "artist": "Imagine Dragons", "streams": "6,515,881", "peak": "16", "previous": "97", "streak": "135", "release_date": "Jun 23, 2017", "first_entry": "Feb 9, 2017", "first_entry_pos": "73", "total_weeks": "135", "producers": "Mattman & Robin", "songwriters": "Justin Tranter, Ben McKee, Dan Reynolds, Daniel Platzman, Mattias Larsson, Robin Fredriksson, Wayne Sermon", "source": "Kid Ina Korner / Interscope"}, {"week": "2019-09-05", "rank": 97, "song": "Miss Americana & The Heartbreak Prince", "artist": "Taylor Swift", "streams": "6,464,373", "peak": "30", "previous": "30", "streak": "2", "release_date": "Aug 23, 2019", "first_entry": "Aug 29, 2019", "first_entry_pos": "30", "total_weeks": "2", "producers": "Joel Little, Taylor Swift", "songwriters": "Joel Little, Taylor Swift", "source": "Taylor Swift"}, {"week": "2019-09-05", "rank": 98, "song": "Don't Call Me Up", "artist": "Mabel", "streams": "6,457,846", "peak": "11", "previous": "95", "streak": "31", "release_date": "Jan 18, 2019", "first_entry": "Feb 7, 2019", "first_entry_pos": "94", "total_weeks": "31", "producers": "Steve Mac", "songwriters": "Steve Mac, kamille, Mabel Mcvey", "source": "Polydor Records"}, {"week": "2019-09-05", "rank": 99, "song": "SOS (feat. Aloe Blacc)", "artist": "Avicii, Aloe Blacc", "streams": "6,437,542", "peak": "4", "previous": "92", "streak": "22", "release_date": "Jun 6, 2019", "first_entry": "Apr 11, 2019", "first_entry_pos": "157", "total_weeks": "22", "producers": "Tim Bergling, Albin Nedler, Kristoffer Fogelmark", "songwriters": "Albin Nedler, Kandi Burruss, Kevin Briggs, Kristoffer Fogelmark, Tameka Cottle, Tim Bergling", "source": "Universal Music AB"}, {"week": "2019-09-05", "rank": 100, "song": "I Think He Knows", "artist": "Taylor Swift", "streams": "6,378,238", "peak": "31", "previous": "31", "streak": "2", "release_date": "Aug 23, 2019", "first_entry": "Aug 29, 2019", "first_entry_pos": "31", "total_weeks": "2", "producers": "Jack Antonoff, Taylor Swift", "songwriters": "Jack Antonoff, Taylor Swift", "source": "Taylor Swift"}, {"week": "2019-09-05", "rank": 101, "song": "Roller", "artist": "Apache 207", "streams": "6,356,307", "peak": "102", "previous": "116", "streak": "2", "release_date": "Aug 23, 2019", "first_entry": "Aug 29, 2019", "first_entry_pos": "116", "total_weeks": "2", "producers": "Suena Lucry", "songwriters": "Jennifer Allendoerfer, Luis Cruz, Volkan Yaman", "source": "Four Music Local"}, {"week": "2019-09-05", "rank": 102, "song": "Shape of You", "artist": "Ed Sheeran", "streams": "6,307,292", "peak": "1", "previous": "93", "streak": "139", "release_date": "Mar 3, 2017", "first_entry": "Jan 12, 2017", "first_entry_pos": "1", "total_weeks": "139", "producers": "Steve Mac", "songwriters": "Johnny McDaid, Steve Mac, Ed Sheeran, Kandi Burruss, Kevin Briggs, Tameka Cottle", "source": "Atlantic Records UK"}, {"week": "2019-09-05", "rank": 103, "song": "Tal Vez", "artist": "Paulo Londra", "streams": "6,250,386", "peak": "24", "previous": "105", "streak": "22", "release_date": "May 23, 2019", "first_entry": "Apr 11, 2019", "first_entry_pos": "84", "total_weeks": "22", "producers": "OvyOnTheDrums", "songwriters": "Daniel Echavarria Oviedo, Cristian Salazar, Paulo Ezequiel Londra", "source": "WEA Latina"}, {"week": "2019-09-05", "rank": 104, "song": "bury a friend", "artist": "Billie Eilish", "streams": "6,239,632", "peak": "2", "previous": "108", "streak": "32", "release_date": "Mar 29, 2019", "first_entry": "Jan 31, 2019", "first_entry_pos": "110", "total_weeks": "32", "producers": "Finneas O'Connell", "songwriters": "Finneas O'Connell, Billie Eilish O'Connell", "source": "Darkroom/Interscope Records"}, {"week": "2019-09-05", "rank": 105, "song": "The Archer", "artist": "Taylor Swift", "streams": "6,205,040", "peak": "33", "previous": "36", "streak": "2", "release_date": "Aug 23, 2019", "first_entry": "Jul 25, 2019", "first_entry_pos": "105", "total_weeks": "6", "producers": "Jack Antonoff, Taylor Swift", "songwriters": "Jack Antonoff, Taylor Swift", "source": "Taylor Swift"}, {"week": "2019-09-05", "rank": 106, "song": "Shots", "artist": "Lil Tecca", "streams": "6,131,471", "peak": "107", "previous": "\u2014", "streak": "1", "release_date": "Aug 30, 2019", "first_entry": "Sep 5, 2019", "first_entry_pos": "107", "total_weeks": "1", "producers": "Nick Mira, Taz Taylor", "songwriters": "Nick Mira, Taz Taylor, Tyler-Justin Anthony Sharpe", "source": "Republic Records"}, {"week": "2019-09-05", "rank": 107, "song": "Pop Out (feat. Lil Tjay)", "artist": "Polo G, Lil Tjay", "streams": "6,125,584", "peak": "40", "previous": "101", "streak": "20", "release_date": "Jun 7, 2019", "first_entry": "Apr 25, 2019", "first_entry_pos": "142", "total_weeks": "20", "producers": "JD On Tha Track, Iceberg", "songwriters": "Dylan Berg, Jo\u00e3o Victor Alba Duarte, Lil Tjay, Polo G", "source": "Columbia"}, {"week": "2019-09-05", "rank": 108, "song": "Cornelia Street", "artist": "Taylor Swift", "streams": "6,098,851", "peak": "35", "previous": "35", "streak": "2", "release_date": "Aug 23, 2019", "first_entry": "Aug 29, 2019", "first_entry_pos": "35", "total_weeks": "2", "producers": "Jack Antonoff, Taylor Swift", "songwriters": "Taylor Swift", "source": "Taylor Swift"}, {"week": "2019-09-05", "rank": 109, "song": "Goteo", "artist": "Duki", "streams": "6,087,403", "peak": "110", "previous": "131", "streak": "4", "release_date": "Aug 7, 2019", "first_entry": "Aug 15, 2019", "first_entry_pos": "146", "total_weeks": "4", "producers": "Juan Thomas Santos", "songwriters": "Mauro Ezequiel Lombardo", "source": "SSJ Records / DALE PLAY Records"}, {"week": "2019-09-05", "rank": 110, "song": "Baila Conmigo (feat. Kelly Ruiz)", "artist": "Dayvi, Victor Cardenas, Kelly Ru\u00edz", "streams": "6,080,156", "peak": "104", "previous": "111", "streak": "6", "release_date": "Sep 12, 2019", "first_entry": "Aug 1, 2019", "first_entry_pos": "162", "total_weeks": "6", "producers": "Victor Cardenas, David S\u00e1nchez", "songwriters": "David S\u00e1nchez Gonzalez (Daivy), Kelly Paola Ruiz Moncada, V\u00edctor Alonso C\u00e1rdenas Ospina", "source": "Sony Music M\u00e9xico"}, {"week": "2019-09-05", "rank": 111, "song": "Atr\u00e9vete", "artist": "Nicky Jam, Sech", "streams": "6,064,034", "peak": "112", "previous": "115", "streak": "5", "release_date": "Nov 1, 2019", "first_entry": "Aug 8, 2019", "first_entry_pos": "146", "total_weeks": "5", "producers": "D\u00edmelo Flow", "songwriters": "Carlos Isa\u00edas Morales Williams \"Sech\", Dimelo Flow, JHONATTAN REYES, JOSHUA J. M\u00c9NDEZ, Jorge Vald\u00e9s (D\u00edmelo Flow), Juan Diego Medina, MANUEL E. CORT\u00c9S, Nick Rivera Caminero \"Nicky Jam\"", "source": "Sony Music Latin"}, {"week": "2019-09-05", "rank": 112, "song": "Cuaderno", "artist": "Dalex, Nicky Jam, Justin Quiles, Sech, Lenny Tav\u00e1rez, Feid, Rafa Pab\u00f6n", "streams": "6,051,114", "peak": "66", "previous": "110", "streak": "15", "release_date": "May 10, 2019", "first_entry": "May 30, 2019", "first_entry_pos": "185", "total_weeks": "15", "producers": "D\u00edmelo Flow, Wain", "songwriters": "Carlos Isaias Morales Williams, Digi, Dimelo Flow, Salom\u00f3n Villada Hoyos, Ivo Alfredo Thomas Serue, JOSHUA MENDEZ, Julio Manuel Gonz\u00e1lez Tav\u00e1rez, Justin Quiles, Nick Rivera Caminero, PEDRO DAVID DALECCIO, Rafael E. Pabon Navedo", "source": "Rich Music/Ingrooves Records"}, {"week": "2019-09-05", "rank": 113, "song": "London Boy", "artist": "Taylor Swift", "streams": "6,031,403", "peak": "37", "previous": "37", "streak": "2", "release_date": "Aug 23, 2019", "first_entry": "Aug 29, 2019", "first_entry_pos": "37", "total_weeks": "2", "producers": "Jack Antonoff, Taylor Swift", "songwriters": "Cautious Clay, Jack Antonoff, Mark Spears, Taylor Swift", "source": "Taylor Swift"}, {"week": "2019-09-05", "rank": 114, "song": "Girls Like You (feat. Cardi B) - Cardi B Version", "artist": "Maroon 5, Cardi B", "streams": "6,019,223", "peak": "2", "previous": "123", "streak": "66", "release_date": "Jun 15, 2018", "first_entry": "Jun 7, 2018", "first_entry_pos": "22", "total_weeks": "66", "producers": "Jason Evigan, Cirkut", "songwriters": "Brittany Talia Hazzard, Gian Stone, Henry Walter, Jason Evigan, Adam Levine, Belcalis Almanzar", "source": "Interscope Records*"}, {"week": "2019-09-05", "rank": 115, "song": "goosebumps", "artist": "Travis Scott", "streams": "6,014,839", "peak": "60", "previous": "\u2014", "streak": "1", "release_date": "Sep 16, 2016", "first_entry": "Jan 5, 2017", "first_entry_pos": "192", "total_weeks": "109", "producers": "Cardo Got Wings, CuBeatz, YeX", "songwriters": "Kevin Gomringer (of CuBeatz), Ronald LaTour, Tim Gomringer, Brock Korsan, Daveon Jackson, Jacques Webster, Kendrick Duckworth", "source": "Cactus Jack / Epic"}, {"week": "2019-09-05", "rank": 116, "song": "Let Me Down Slowly", "artist": "Alec Benjamin", "streams": "6,005,622", "peak": "27", "previous": "127", "streak": "34", "release_date": "Nov 16, 2018", "first_entry": "Jun 28, 2018", "first_entry_pos": "184", "total_weeks": "39", "producers": "Nolan Lambroza", "songwriters": "Michael Pollack, Nolan Lambroza, Alec Benjamin, Michale Pollack", "source": "2018"}, {"week": "2019-09-05", "rank": 117, "song": "High Hopes", "artist": "Panic! At The Disco", "streams": "5,995,676", "peak": "9", "previous": "122", "streak": "63", "release_date": "Jun 22, 2018", "first_entry": "Jun 28, 2018", "first_entry_pos": "85", "total_weeks": "63", "producers": "Jake Sinclair, Jonas Jeberg, Jonny Coffer", "songwriters": "Ilsey Juber, Jake Sinclair, Jenny Owen Youngs, Sam Hollander, Tayla Parx, Brendon Urie, Jonas Jeberg, Lauren Pritchard, William Lobbin Bean", "source": "DCD2 / Fueled By Ramen"}, {"week": "2019-09-05", "rank": 118, "song": "Runaway", "artist": "Sebastian Yatra, Daddy Yankee, NATTI NATASHA, Jonas Brothers", "streams": "5,989,858", "peak": "57", "previous": "99", "streak": "11", "release_date": "Jun 21, 2019", "first_entry": "Jun 27, 2019", "first_entry_pos": "57", "total_weeks": "11", "producers": "Andr\u00e9s Torres, Mauricio Rengifo", "songwriters": "Andr\u00e9s Torres, Mauricio Rengifo, Daddy Yankee, Joseph Angel, NATTI NATASHA, Raphy Pina, Sebasti\u00e1n Obando Giraldo", "source": "UMLE - Latino"}, {"week": "2019-09-05", "rank": 119, "song": "Baguettes in the Face (feat. NAV, Playboi Carti & A Boogie Wit da Hoodie)", "artist": "Mustard, NAV, Playboi Carti, A Boogie Wit da Hoodie", "streams": "5,968,121", "peak": "120", "previous": "134", "streak": "10", "release_date": "Jun 28, 2019", "first_entry": "Jul 4, 2019", "first_entry_pos": "158", "total_weeks": "10", "producers": "Mustard, Larry Jayy", "songwriters": "Artist Julius Dubose, Dijon McFarlane, Jordan Carter, Larry Sanders, Navraj Singh Goraya", "source": "10 Summers Records/Interscope Records"}, {"week": "2019-09-05", "rank": 120, "song": "Pa M\u00ed - Remix", "artist": "Dalex, Rafa Pab\u00f6n, KHEA, Sech, Feid, Cazzu, Lenny Tav\u00e1rez", "streams": "5,932,396", "peak": "17", "previous": "117", "streak": "27", "release_date": "May 10, 2019", "first_entry": "Mar 7, 2019", "first_entry_pos": "149", "total_weeks": "27", "producers": "D\u00edmelo Flow, Rike Music, Wally", "songwriters": "Carlos Isaias Morales Williams, Dimelo Flow, Salom\u00f3n Villada Hoyos, Ivo Alfredo Thomas Serue, JOSHUA MENDEZ, Julieta Cazzuchelli, Julio Manuel Gonz\u00e1lez Tav\u00e1rez, PEDRO DAVID DALECCIO, Rafael E. Pabon Navedo", "source": "Rich Music/Ingrooves Records"}, {"week": "2019-09-05", "rank": 121, "song": "Hot (feat. Gunna)", "artist": "Young Thug, Gunna", "streams": "5,925,621", "peak": "88", "previous": "132", "streak": "3", "release_date": "Aug 16, 2019", "first_entry": "Aug 22, 2019", "first_entry_pos": "88", "total_weeks": "3", "producers": "", "songwriters": "", "source": "300 Entertainment/Atl"}, {"week": "2019-09-05", "rank": 122, "song": "The Git Up", "artist": "Blanco Brown", "streams": "5,883,765", "peak": "64", "previous": "113", "streak": "12", "release_date": "Oct 10, 2019", "first_entry": "Jun 20, 2019", "first_entry_pos": "190", "total_weeks": "12", "producers": "", "songwriters": "Bennie Amey III", "source": "Broken Bow Records"}, {"week": "2019-09-05", "rank": 123, "song": "Youngblood", "artist": "5 Seconds of Summer", "streams": "5,883,185", "peak": "8", "previous": "148", "streak": "73", "release_date": "Jun 15, 2018", "first_entry": "Apr 19, 2018", "first_entry_pos": "117", "total_weeks": "73", "producers": "Andrew Watt, Louis Bell", "songwriters": "Ali Tamposi, Andrew Watt, Louis Bell, Ashton Irwin, Calum Hood, Luke Hemmings", "source": "Capitol"}, {"week": "2019-09-05", "rank": 124, "song": "Cinnamon Girl", "artist": "Lana Del Rey", "streams": "5,880,972", "peak": "125", "previous": "\u2014", "streak": "1", "release_date": "Aug 30, 2019", "first_entry": "Sep 5, 2019", "first_entry_pos": "125", "total_weeks": "1", "producers": "Lana Del Rey, Jack Antonoff", "songwriters": "Jack Antonoff, Lana Del Rey", "source": "Polydor Records"}, {"week": "2019-09-05", "rank": 125, "song": "Right Back (feat. A Boogie Wit Da Hoodie)", "artist": "Khalid, A Boogie Wit da Hoodie", "streams": "5,818,316", "peak": "112", "previous": "119", "streak": "4", "release_date": "Aug 13, 2019", "first_entry": "Aug 15, 2019", "first_entry_pos": "115", "total_weeks": "4", "producers": "Stargate, Mike \"Scribz\" Riley, Charlie Handsome, Denis Kosiak", "songwriters": "Mikkel Eriksen (of Stargate), Rodney Jerkins, Ryan Vojtesak, Tor Erik Hermansen, Brenda Russell, Denis Kosiak, Dwayne Carter, Gary Kemp, Japhe Tejeda, Jasper Cameron, Joe Thomas, Jolyon Skinner, Julius Dubose, Khalid Robinson, Maurice Sinclair, Michelle Williams, Mike \"Scribz\" Riley, Mikkel Storleer Eriksen", "source": "Right Hand Music Group, LLC/RCA Records"}, {"week": "2019-09-05", "rank": 126, "song": "Lucid Dreams", "artist": "Juice WRLD", "streams": "5,800,631", "peak": "3", "previous": "147", "streak": "69", "release_date": "Dec 10, 2018", "first_entry": "May 17, 2018", "first_entry_pos": "125", "total_weeks": "69", "producers": "Nick Mira", "songwriters": "Danny Lee Snodgrass, Jr., Juice WRLD, Dominic Miller, Nick Mira, Sting", "source": "Juice WRLD Mixtape / ISR P&D"}, {"week": "2019-09-05", "rank": 127, "song": "Call You Mine", "artist": "The Chainsmokers, Bebe Rexha", "streams": "5,780,255", "peak": "22", "previous": "124", "streak": "14", "release_date": "Dec 6, 2019", "first_entry": "Jun 6, 2019", "first_entry_pos": "33", "total_weeks": "14", "producers": "The Chainsmokers, Andrew Watt", "songwriters": "Alexandra Tamposi, Andrew Wotman, Steve Mac, Alex Pall, Andrew Taggart, Norman Whitfield, Tony Ann", "source": "Disruptor Records/Columbia"}, {"week": "2019-09-05", "rank": 128, "song": "Only Human", "artist": "Jonas Brothers", "streams": "5,750,956", "peak": "31", "previous": "143", "streak": "13", "release_date": "Jun 7, 2019", "first_entry": "Jun 13, 2019", "first_entry_pos": "31", "total_weeks": "13", "producers": "Shellback", "songwriters": "Joe Jonas, Johan Schuster, Kevin Jonas, Nick Jonas", "source": "Jonas Brothers Recording"}, {"week": "2019-09-05", "rank": 129, "song": "All Around The World (La La La)", "artist": "R3HAB, A Touch Of Class", "streams": "5,681,368", "peak": "59", "previous": "125", "streak": "13", "release_date": "Jul 26, 2019", "first_entry": "Jun 13, 2019", "first_entry_pos": "124", "total_weeks": "13", "producers": "R3HAB", "songwriters": "Alex Christensen, Alexei Potekhin, Peter K\u00f6nemann, Sergei Zhukov", "source": "Casablanca Records"}, {"week": "2019-09-05", "rank": 130, "song": "Mad Love", "artist": "Mabel", "streams": "5,643,905", "peak": "54", "previous": "118", "streak": "13", "release_date": "Aug 2, 2019", "first_entry": "Jun 13, 2019", "first_entry_pos": "103", "total_weeks": "13", "producers": "Steve Mac", "songwriters": "Camille Purcell, Steve Mac, Mabel Mcvey", "source": "Polydor Records"}, {"week": "2019-09-05", "rank": 131, "song": "Be Honest (feat. Burna Boy)", "artist": "Jorja Smith, Burna Boy", "streams": "5,633,996", "peak": "121", "previous": "121", "streak": "3", "release_date": "Aug 16, 2019", "first_entry": "Aug 22, 2019", "first_entry_pos": "143", "total_weeks": "3", "producers": "Cadenza, IzyBeats, Kyle Stemberger", "songwriters": "Amira Benameur, Andron Francois Cross, Oliver Rodigan, Damini Ogulu, Jorja Smith", "source": "FAMM"}, {"week": "2019-09-05", "rank": 132, "song": "comethru", "artist": "Jeremy Zucker", "streams": "5,630,335", "peak": "111", "previous": "133", "streak": "9", "release_date": "Sep 28, 2018", "first_entry": "Jul 11, 2019", "first_entry_pos": "199", "total_weeks": "9", "producers": "Jeremy Zucker", "songwriters": "Daniel Rakow, Jeremy Zucker", "source": "Republic Records"}, {"week": "2019-09-05", "rank": 133, "song": "Better", "artist": "Khalid", "streams": "5,624,880", "peak": "7", "previous": "137", "streak": "51", "release_date": "Oct 18, 2018", "first_entry": "Sep 20, 2018", "first_entry_pos": "21", "total_weeks": "51", "producers": "Digi, Charlie Handsome, Stargate", "songwriters": "Jamil Chammas, Mikkel Eriksen (of Stargate), Ryan Vojtesak, Tor Erik Hermansen, Khalid Robinson, Mikkel Storleer Eriksen", "source": "Right Hand Music Group, LLC/RCA Records"}, {"week": "2019-09-05", "rank": 134, "song": "Perfect", "artist": "Ed Sheeran", "streams": "5,606,477", "peak": "4", "previous": "146", "streak": "131", "release_date": "Mar 3, 2017", "first_entry": "Mar 9, 2017", "first_entry_pos": "7", "total_weeks": "131", "producers": "Ed Sheeran, Will Hicks", "songwriters": "Ed Sheeran", "source": "Atlantic Records UK"}, {"week": "2019-09-05", "rank": 135, "song": "Ritual", "artist": "Ti\u00ebsto, Jonas Blue, Rita Ora", "streams": "5,563,211", "peak": "72", "previous": "142", "streak": "14", "release_date": "May 31, 2019", "first_entry": "Jun 6, 2019", "first_entry_pos": "78", "total_weeks": "14", "producers": "Ti\u00ebsto, Jonas Blue, Stonebank", "songwriters": "Fraser T. Smith, Grace Barker, Wayne Hector, Guy Robin, Michael Stonebank, Tijs Verwest", "source": "Universal Music, a division of Universal International Music BV"}, {"week": "2019-09-05", "rank": 136, "song": "Won't Be Late (feat. Drake)", "artist": "Swae Lee, Drake", "streams": "5,542,102", "peak": "68", "previous": "103", "streak": "3", "release_date": "Aug 16, 2019", "first_entry": "Aug 22, 2019", "first_entry_pos": "68", "total_weeks": "3", "producers": "Tekno, Mike WiLL Made-It", "songwriters": "Kelechukwu Augustine, Michael Williams, A. Graham, Khalif Brown", "source": "Eardruma Records/Interscope Records"}, {"week": "2019-09-05", "rank": 137, "song": "HP", "artist": "Maluma", "streams": "5,533,508", "peak": "18", "previous": "138", "streak": "27", "release_date": "May 17, 2019", "first_entry": "Mar 7, 2019", "first_entry_pos": "72", "total_weeks": "27", "producers": "\u00c9dgar Barrera \"Edge\", Madmusick", "songwriters": "Edgar Barrera, Vibarco, Giencarlos Rivera, Jonathan Rivera, Juan Luis Londo\u00f1o, Vicente Barco", "source": "Sony Music Latin"}, {"week": "2019-09-05", "rank": 138, "song": "Taki Taki (feat. Selena Gomez, Ozuna & Cardi B)", "artist": "DJ Snake, Selena Gomez, Ozuna, Cardi B", "streams": "5,528,440", "peak": "1", "previous": "141", "streak": "49", "release_date": "Jul 25, 2019", "first_entry": "Oct 4, 2018", "first_entry_pos": "1", "total_weeks": "49", "producers": "DJ Snake", "songwriters": "Juan Carlos Ozuna Rosado, Juan G. Rivera, Ava Brignol, Belcalis Almanzar, Jorden Thorpe, Selena Gomez, William Grigahcine", "source": "DJ Snake Music Productions Limited"}, {"week": "2019-09-05", "rank": 139, "song": "BUTTERFLY EFFECT", "artist": "Travis Scott", "streams": "5,522,873", "peak": "38", "previous": "\u2014", "streak": "1", "release_date": "Aug 3, 2018", "first_entry": "May 25, 2017", "first_entry_pos": "164", "total_weeks": "61", "producers": "Murda Beatz", "songwriters": "Shane Lindstrom, Donald Paton, Jacques Webster", "source": "Cactus Jack / Epic"}, {"week": "2019-09-05", "rank": 140, "song": "MIDDLE CHILD", "artist": "J. Cole", "streams": "5,516,836", "peak": "2", "previous": "144", "streak": "33", "release_date": "Jan 23, 2019", "first_entry": "Jan 24, 2019", "first_entry_pos": "111", "total_weeks": "33", "producers": "T-Minus, J. Cole", "songwriters": "T-Minus, J. Cole", "source": "Dreamville, Inc., Under exclusive license to Roc Nation Records"}, {"week": "2019-09-05", "rank": 141, "song": "Shotta Flow (feat. Blueface) - Remix", "artist": "NLE Choppa, Blueface", "streams": "5,516,101", "peak": "97", "previous": "128", "streak": "8", "release_date": "Dec 23, 2019", "first_entry": "Jul 18, 2019", "first_entry_pos": "168", "total_weeks": "8", "producers": "Midas 800", "songwriters": "Bryson Potts, Donald Bailey Jr., Johnathan Michael Porter", "source": "Warner Records"}, {"week": "2019-09-05", "rank": 142, "song": "Si Supieras", "artist": "Daddy Yankee, Wisin & Yandel", "streams": "5,490,363", "peak": "98", "previous": "126", "streak": "10", "release_date": "Jun 28, 2019", "first_entry": "Jul 4, 2019", "first_entry_pos": "133", "total_weeks": "10", "producers": "Luny, Tainy", "songwriters": "Gaby Music, Marco Masis, Daddy Yankee, Eric Joel Lobo, Francisco Salda\u00f1a, Raphy Pina, Wisin, Yandel", "source": "El Cartel Records (EC3)"}, {"week": "2019-09-05", "rank": 143, "song": "Boy With Luv (feat. Halsey)", "artist": "BTS, Halsey", "streams": "5,464,453", "peak": "3", "previous": "139", "streak": "21", "release_date": "Apr 12, 2019", "first_entry": "Apr 18, 2019", "first_entry_pos": "3", "total_weeks": "21", "producers": "", "songwriters": "Emily Weisband, Melanie Joy Fontana, \u201chitman\u201d bang, Halsey, Michel \"Lindgren\" Schulz, Pdogg, RM, SUGA, j-hope", "source": "BIGHIT MUSIC"}, {"week": "2019-09-05", "rank": 144, "song": "Be Alright", "artist": "Dean Lewis", "streams": "5,463,817", "peak": "12", "previous": "154", "streak": "59", "release_date": "Mar 22, 2019", "first_entry": "Jul 26, 2018", "first_entry_pos": "136", "total_weeks": "59", "producers": "Nick Atkinson, Edward Holloway, Dylan Nash", "songwriters": "Jon Hume, Dean Lewis", "source": "Universal Music Australia Pty. Ltd."}, {"week": "2019-09-05", "rank": 145, "song": "i'm so tired...", "artist": "Lauv, Troye Sivan", "streams": "5,463,535", "peak": "18", "previous": "158", "streak": "32", "release_date": "Mar 6, 2020", "first_entry": "Jan 31, 2019", "first_entry_pos": "34", "total_weeks": "32", "producers": "Lauv, Oscar G\u00f6rres", "songwriters": "Ari Leff, Brett McLaughlin, Michael Pollack, Oscar G\u00f6rres, Troye Sivan Mellet", "source": "Lauv"}, {"week": "2019-09-05", "rank": 146, "song": "Say You Won't Let Go", "artist": "James Arthur", "streams": "5,461,083", "peak": "7", "previous": "151", "streak": "36", "release_date": "Oct 28, 2016", "first_entry": "Dec 29, 2016", "first_entry_pos": "10", "total_weeks": "140", "producers": "Alex Beitzke, Bradley Spence", "songwriters": "James Arthur, Neil Ormandy, Andrew Frampton, Daniel O'Donoghue, Mark Sheehan, Stephen Kipner, Steven Solomon", "source": "Columbia"}, {"week": "2019-09-05", "rank": 147, "song": "Death By A Thousand Cuts", "artist": "Taylor Swift", "streams": "5,439,948", "peak": "42", "previous": "42", "streak": "2", "release_date": "Aug 23, 2019", "first_entry": "Aug 29, 2019", "first_entry_pos": "42", "total_weeks": "2", "producers": "Jack Antonoff, Taylor Swift", "songwriters": "Jack Antonoff, Taylor Swift", "source": "Taylor Swift"}, {"week": "2019-09-05", "rank": 148, "song": "Cross Me (feat. Chance the Rapper & PnB Rock)", "artist": "Ed Sheeran, Chance the Rapper, PnB Rock", "streams": "5,428,437", "peak": "9", "previous": "107", "streak": "15", "release_date": "Jul 12, 2019", "first_entry": "May 30, 2019", "first_entry_pos": "9", "total_weeks": "15", "producers": "FRED", "songwriters": "Chancelor Bennett, Ed Sheeran, Fred Gibson, Rakim Hasheem Allen", "source": "Atlantic Records UK"}, {"week": "2019-09-05", "rank": 149, "song": "I Like Me Better", "artist": "Lauv", "streams": "5,413,917", "peak": "29", "previous": "167", "streak": "118", "release_date": "May 31, 2018", "first_entry": "Jun 8, 2017", "first_entry_pos": "175", "total_weeks": "118", "producers": "Lauv", "songwriters": "Ari Leff, Michael Matosic", "source": "Lauv"}, {"week": "2019-09-05", "rank": 150, "song": "EARFQUAKE", "artist": "Tyler, The Creator", "streams": "5,412,240", "peak": "6", "previous": "145", "streak": "16", "release_date": "May 17, 2019", "first_entry": "May 23, 2019", "first_entry_pos": "6", "total_weeks": "16", "producers": "Tyler, The Creator", "songwriters": "Jordan Carter, Tyler Okonma", "source": "Columbia"}, {"week": "2019-09-05", "rank": 151, "song": "Antisocial (with Travis Scott)", "artist": "Ed Sheeran, Travis Scott", "streams": "5,406,099", "peak": "7", "previous": "140", "streak": "8", "release_date": "Jul 12, 2019", "first_entry": "Jul 18, 2019", "first_entry_pos": "7", "total_weeks": "8", "producers": "FRED", "songwriters": "Ed Sheeran, Fred Gibson, Jacques Webster, Joseph Saddler", "source": "Atlantic Records UK"}, {"week": "2019-09-05", "rank": 152, "song": "La Boca - Remix", "artist": "Mau y Ricky, Camilo, Lunay", "streams": "5,358,652", "peak": "140", "previous": "150", "streak": "6", "release_date": "Jul 17, 2019", "first_entry": "Aug 1, 2019", "first_entry_pos": "178", "total_weeks": "6", "producers": "Jon Leone, Haze", "songwriters": "Tainy, Camilo Echeverry, Jefnier Osorio Moreno, Jon Leone, Juan Morelli, Marco Masis \"Tainy\", Mau Montaner, Ricky Montaner", "source": "Sony Music Latin"}, {"week": "2019-09-05", "rank": 153, "song": "Go Loko (feat. Tyga, Jon Z)", "artist": "YG, Tyga, Jon Z", "streams": "5,357,020", "peak": "38", "previous": "135", "streak": "18", "release_date": "May 24, 2019", "first_entry": "May 9, 2019", "first_entry_pos": "153", "total_weeks": "18", "producers": "Mustard", "songwriters": "Jonathan Resto Qui\u00f1ones, Dijon McFarlane, Keenon Jackson, Michael Stevenson, Shah Rukh Zaman Khan", "source": "Def Jam Recordings"}, {"week": "2019-09-05", "rank": 154, "song": "2002", "artist": "Anne-Marie", "streams": "5,325,514", "peak": "27", "previous": "171", "streak": "72", "release_date": "Apr 27, 2018", "first_entry": "Apr 26, 2018", "first_entry_pos": "76", "total_weeks": "72", "producers": "Steve Mac", "songwriters": "Anne-Marie Nicholson, Benjamin Levin, Julia Michaels, Max Martin, Steve Mac, Ed Sheeran", "source": "Atlantic Records UK"}, {"week": "2019-09-05", "rank": 155, "song": "I Warned Myself", "artist": "Charlie Puth", "streams": "5,316,743", "peak": "156", "previous": "177", "streak": "2", "release_date": "Aug 21, 2019", "first_entry": "Aug 29, 2019", "first_entry_pos": "177", "total_weeks": "2", "producers": "", "songwriters": "benny blanco", "source": "Artist Partner"}, {"week": "2019-09-05", "rank": 156, "song": "Don't Stop Me Now - Remastered 2011", "artist": "Queen", "streams": "5,310,940", "peak": "51", "previous": "153", "streak": "45", "release_date": "Nov 10, 1978", "first_entry": "Nov 1, 2018", "first_entry_pos": "186", "total_weeks": "45", "producers": "Queen, Roy Thomas Baker", "songwriters": "Brian May, Freddie Mercury", "source": "Hollywood Records"}, {"week": "2019-09-05", "rank": 157, "song": "Mariners Apartment Complex", "artist": "Lana Del Rey", "streams": "5,308,425", "peak": "141", "previous": "\u2014", "streak": "1", "release_date": "Aug 30, 2019", "first_entry": "Sep 20, 2018", "first_entry_pos": "141", "total_weeks": "2", "producers": "Lana Del Rey, Jack Antonoff", "songwriters": "Jack Antonoff, Lana Del Rey", "source": "Polydor Records"}, {"week": "2019-09-05", "rank": 158, "song": "Bezerk (feat. A$AP Ferg)", "artist": "Big Sean, Hit-Boy, A$AP Ferg", "streams": "5,275,170", "peak": "159", "previous": "\u2014", "streak": "1", "release_date": "Aug 26, 2019", "first_entry": "Sep 5, 2019", "first_entry_pos": "159", "total_weeks": "1", "producers": "Hit-Boy", "songwriters": "Chauncey Hollis, Darold Brown, Dustin James Corbett, Greg Davis, Sean Anderson", "source": "Getting Out Our Dreams, Inc./Def Jam Recordings"}, {"week": "2019-09-05", "rank": 159, "song": "Bellacoso", "artist": "Residente, Bad Bunny", "streams": "5,272,362", "peak": "83", "previous": "130", "streak": "6", "release_date": "Jul 26, 2019", "first_entry": "Aug 1, 2019", "first_entry_pos": "108", "total_weeks": "6", "producers": "Residente, Trooko", "songwriters": "Freddy Montalvo, Jos\u00e9 Carlos Cruz, Benito Antonio Mart\u00ednez Ocasio, Jeffrey Pe\u00f1alva \"Trooko\", Jes\u00fas Alberto Molina Prato, Luis Romero, Ren\u00e9 P\u00e9rez Joglar (Residente), Urbani Mota", "source": "5020 Records"}, {"week": "2019-09-05", "rank": 160, "song": "SAD!", "artist": "XXXTENTACION", "streams": "5,265,450", "peak": "1", "previous": "155", "streak": "79", "release_date": "Mar 16, 2018", "first_entry": "Mar 8, 2018", "first_entry_pos": "12", "total_weeks": "79", "producers": "John Cunningham", "songwriters": "Jahseh Onfroy, John Cunningham", "source": "Bad Vibes Forever, LLC"}, {"week": "2019-09-05", "rank": 161, "song": "Love song", "artist": "Lana Del Rey", "streams": "5,187,928", "peak": "162", "previous": "\u2014", "streak": "1", "release_date": "Aug 30, 2019", "first_entry": "Sep 5, 2019", "first_entry_pos": "162", "total_weeks": "1", "producers": "Lana Del Rey, Jack Antonoff", "songwriters": "Jack Antonoff, Lana Del Rey", "source": "Polydor Records"}, {"week": "2019-09-05", "rank": 162, "song": "break up with your girlfriend, i'm bored", "artist": "Ariana Grande", "streams": "5,150,390", "peak": "2", "previous": "166", "streak": "30", "release_date": "Feb 8, 2019", "first_entry": "Feb 14, 2019", "first_entry_pos": "2", "total_weeks": "30", "producers": "Max Martin, ILYA", "songwriters": "Ariana Grande, Ilya Salmanzadeh, Max Martin, Savan Kotecha, Kandi Burruss, Kevin Briggs", "source": "Republic Records"}, {"week": "2019-09-05", "rank": 163, "song": "Going Bad (feat. Drake)", "artist": "Meek Mill, Drake", "streams": "5,135,500", "peak": "11", "previous": "164", "streak": "40", "release_date": "Nov 30, 2018", "first_entry": "Dec 6, 2018", "first_entry_pos": "11", "total_weeks": "40", "producers": "Wheezy", "songwriters": "Meek Mill, Wesley Glass, Westen Weiss, A. Graham", "source": "MMG/Atlantic"}, {"week": "2019-09-05", "rank": 164, "song": "UP IN SMOKE", "artist": "RIN", "streams": "5,126,611", "peak": "165", "previous": "\u2014", "streak": "1", "release_date": "Aug 30, 2019", "first_entry": "Sep 5, 2019", "first_entry_pos": "165", "total_weeks": "1", "producers": "RIN, Alexis Troy, Minhtendo", "songwriters": "Alexis Troy, Anh Minh Vo, Renato Simunovic", "source": "GOLD LEAGUE/DIVISION"}, {"week": "2019-09-05", "rank": 165, "song": "MIA", "artist": "Bad Bunny, Drake", "streams": "5,082,391", "peak": "1", "previous": "152", "streak": "47", "release_date": "Dec 23, 2018", "first_entry": "Oct 18, 2018", "first_entry_pos": "1", "total_weeks": "47", "producers": "DJ Luian, Mambo Kingz", "songwriters": "Luian Malave Nieves, A. Graham, Benito Martinez, Edgar Semper Vargas, Elvin Pe\u00f1a, Francis Diaz, Henry Pulman, Joseph Negron Velez, Noah Assad, Xavier Semper Vargas", "source": "Rimas Entertainment LLC"}, {"week": "2019-09-05", "rank": 166, "song": "Swervin (feat. 6ix9ine)", "artist": "A Boogie Wit da Hoodie, 6ix9ine", "streams": "5,041,974", "peak": "25", "previous": "159", "streak": "36", "release_date": "Dec 21, 2018", "first_entry": "Jan 3, 2019", "first_entry_pos": "192", "total_weeks": "36", "producers": "London On Da Track", "songwriters": "London Holmes, Andrew Green, Artist Dubose, Aubrey Robinson, Daniel Hernandez, Kevin Richardson, Roark Bailey", "source": "Highbridge the Label / Atlantic Records"}, {"week": "2019-09-05", "rank": 167, "song": "Another One Bites The Dust - Remastered 2011", "artist": "Queen", "streams": "5,039,369", "peak": "36", "previous": "169", "streak": "45", "release_date": "Jun 27, 1980", "first_entry": "Nov 1, 2018", "first_entry_pos": "177", "total_weeks": "45", "producers": "Queen", "songwriters": "John Deacon", "source": "Hollywood Records"}, {"week": "2019-09-05", "rank": 168, "song": "In My Mind", "artist": "Dynoro, Gigi D'Agostino", "streams": "5,018,953", "peak": "6", "previous": "157", "streak": "61", "release_date": "Jun 8, 2018", "first_entry": "Jul 12, 2018", "first_entry_pos": "121", "total_weeks": "61", "producers": "Dynoro", "songwriters": "Aden Forte, Carlo Montagn\u00e8r, Diego Leoni, Georgina Kingsley, Ivan Gough, Joshua Soon, Luigino Di Agostino, Paolo Sandrini", "source": "Columbia/B1 Recordings"}, {"week": "2019-09-05", "rank": 169, "song": "Rebota - Remix", "artist": "Guaynaa, Nicky Jam, Farruko, Becky G, Sech", "streams": "4,995,998", "peak": "101", "previous": "156", "streak": "7", "release_date": "Jul 12, 2019", "first_entry": "Jul 25, 2019", "first_entry_pos": "148", "total_weeks": "7", "producers": "Enrique L. Pi\u00f1eiro Rivera", "songwriters": "Carlos Isaias Morales Williams, Dimelo Flow, Luian Malav\u00e9, Andy Bauza, Carlos De Jes\u00fas Rodr\u00edguez, Carlos Efren Correa, Edgar W Semper Vargas, Enrique L. Pi\u00f1eiro Rivera, Franklin Jovani Mart\u00ednez, Jean Carlos Santiago Perez, Jorge Vald\u00e9s V\u00e1zquez, Juan Diego Medina, Juan L. Rivera Medina, Kedin Maisonet, Marcos G. P\u00e9rez, Nick Rivera Caminero, Pablo Christian Fuentes, Rebbeca Marie Gomez, Wander Manuel Mendez, Xavier Semper Vargas", "source": "Rebota Remix"}, {"week": "2019-09-05", "rank": 170, "song": "Venice Bitch", "artist": "Lana Del Rey", "streams": "4,976,405", "peak": "171", "previous": "\u2014", "streak": "1", "release_date": "Aug 30, 2019", "first_entry": "Sep 5, 2019", "first_entry_pos": "171", "total_weeks": "1", "producers": "Lana Del Rey, Jack Antonoff", "songwriters": "Jack Antonoff, Lana Del Rey", "source": "Polydor Records"}, {"week": "2019-09-05", "rank": 171, "song": "Thunder", "artist": "Imagine Dragons", "streams": "4,948,148", "peak": "8", "previous": "165", "streak": "123", "release_date": "Jun 23, 2017", "first_entry": "May 4, 2017", "first_entry_pos": "83", "total_weeks": "123", "producers": "Alex Da Kid, Jayson DeZuzio", "songwriters": "A. Grant, Ben McKee, Dan Reynolds, Daniel Platzman, Jayson DeZuzio, Wayne Sermon", "source": "Kid Ina Korner / Interscope"}, {"week": "2019-09-05", "rank": 172, "song": "Hate Me (with Juice WRLD)", "artist": "Ellie Goulding, Juice WRLD", "streams": "4,944,463", "peak": "66", "previous": "109", "streak": "10", "release_date": "Jun 26, 2019", "first_entry": "Jul 4, 2019", "first_entry_pos": "94", "total_weeks": "10", "producers": "Jason Evigan, The Monsters & Strangerz", "songwriters": "Ali Tamposi, Andrew Wotman, Brittany Hazzard, Jarad Higgins, Jason Evigan, Jordan K. Johnson, Marcus Lomax, Pharrell Williams, Stefan Johnson, Ellie Goulding", "source": "Polydor Records"}, {"week": "2019-09-05", "rank": 173, "song": "Here With Me", "artist": "Marshmello, CHVRCHES", "streams": "4,899,366", "peak": "16", "previous": "172", "streak": "26", "release_date": "Mar 8, 2019", "first_entry": "Mar 14, 2019", "first_entry_pos": "43", "total_weeks": "26", "producers": "Marshmello, Steve Mac", "songwriters": "Steve Mac, Iain Cook, Lauren Mayberry, Marshmello, Martin Doherty", "source": "Joytime Collective"}, {"week": "2019-09-05", "rank": 174, "song": "So Am I", "artist": "Ava Max", "streams": "4,880,303", "peak": "41", "previous": "181", "streak": "26", "release_date": "Sep 18, 2020", "first_entry": "Mar 14, 2019", "first_entry_pos": "187", "total_weeks": "26", "producers": "Cirkut", "songwriters": "Gigi Grombacher, Henry Walter, Victor Thell, Amanda Ava Koci, Maria Jane Smith, Martin Sue, Roland Spreckley", "source": "Atlantic Records"}, {"week": "2019-09-05", "rank": 175, "song": "Afterglow", "artist": "Taylor Swift", "streams": "4,879,243", "peak": "50", "previous": "50", "streak": "2", "release_date": "Aug 23, 2019", "first_entry": "Aug 29, 2019", "first_entry_pos": "50", "total_weeks": "2", "producers": "Louis Bell, Frank Dukes, Taylor Swift", "songwriters": "Adam Feeney, Louis Bell, Matthew Tavares, Taylor Swift", "source": "Taylor Swift"}, {"week": "2019-09-05", "rank": 176, "song": "Moonlight", "artist": "XXXTENTACION", "streams": "4,826,988", "peak": "2", "previous": "175", "streak": "77", "release_date": "Mar 16, 2018", "first_entry": "Mar 22, 2018", "first_entry_pos": "14", "total_weeks": "77", "producers": "John Cunningham", "songwriters": "Jahseh Onfroy, John Cunningham", "source": "Bad Vibes Forever, LLC"}, {"week": "2019-09-05", "rank": 177, "song": "Que Mas Pues - Remix", "artist": "Sech, Justin Quiles, Maluma, Nicky Jam, Farruko, Dalex, Lenny Tav\u00e1rez", "streams": "4,797,026", "peak": "70", "previous": "168", "streak": "21", "release_date": "Apr 19, 2019", "first_entry": "Apr 18, 2019", "first_entry_pos": "179", "total_weeks": "21", "producers": "D\u00edmelo Flow, Rike Music, Jhon El Diver", "songwriters": "Carlos Isaias Morales Williams, Jorge Valdes, Carlos Efr\u00e9n Reyes Rosado, JOSHUA MENDEZ, Jhonattan Jacob Reyes, Juan Luis Londo\u00f1o Arias, Justin Quiles, Manuel Enrique Cortes, Nick Rivera Caminero, PEDRO DAVID DALECCIO", "source": "Rich Music/Ingrooves Records"}, {"week": "2019-09-05", "rank": 178, "song": "CANGURO", "artist": "WOS", "streams": "4,793,656", "peak": "133", "previous": "162", "streak": "4", "release_date": "Aug 9, 2019", "first_entry": "Aug 15, 2019", "first_entry_pos": "195", "total_weeks": "4", "producers": "Evlay", "songwriters": "Valent\u00edn Oliva", "source": "DOGUITO Records / DALE PLAY Records"}, {"week": "2019-09-05", "rank": 179, "song": "El Favor (with Nicky Jam & Sech, feat. Farruko, Zion & Lunay)", "artist": "D\u00edmelo Flow, Nicky Jam, Sech, Farruko, Zion, Lunay", "streams": "4,778,297", "peak": "180", "previous": "\u2014", "streak": "1", "release_date": "Aug 30, 2019", "first_entry": "Sep 5, 2019", "first_entry_pos": "180", "total_weeks": "1", "producers": "Jorge Valdez, Manuel Enrique Cortes, Simon Restrepo, Jhonattan Jacob Reyes", "songwriters": "Carlos Isaias Morales Williams, Dimelo Flow, Kevyn Mauricio Cruz Moreno, Carlos Efr\u00e9n Reyes Rosado, Felix Gerardo Ortiz, JOSHUA MENDEZ, Jefnier Osorio, Jhonattan Jacob Reyes, Jorge Valdez, Juan Camilo Vargas, Justin Quiles, Manuel Enrique Cortes, Nick Rivera Caminero, Ramses Herrera, Simon Restrepo", "source": "Rich Music/Interscope Records"}, {"week": "2019-09-05", "rank": 180, "song": "Too Good At Goodbyes", "artist": "Sam Smith", "streams": "4,763,751", "peak": "1", "previous": "182", "streak": "36", "release_date": "Nov 3, 2017", "first_entry": "Sep 14, 2017", "first_entry_pos": "1", "total_weeks": "103", "producers": "Jimmy Napes, Steve Fitzmaurice, Stargate", "songwriters": "James Napier, Mikkel Storleer Eriksen, Tor Erik Hermansen, Sam Smith", "source": "PLG - Capitol"}, {"week": "2019-09-05", "rank": 181, "song": "Nicki Nicole: Bzrp Music Sessions, Vol. 13", "artist": "Bizarrap, Nicki Nicole", "streams": "4,740,528", "peak": "98", "previous": "129", "streak": "3", "release_date": "Aug 14, 2019", "first_entry": "Aug 22, 2019", "first_entry_pos": "98", "total_weeks": "3", "producers": "Bizarrap", "songwriters": "Gonzalo Juli\u00e1n Conde, Nicole Cucco", "source": "DALE PLAY Records"}, {"week": "2019-09-05", "rank": 182, "song": "Small Talk", "artist": "Katy Perry", "streams": "4,739,119", "peak": "38", "previous": "120", "streak": "4", "release_date": "Aug 9, 2019", "first_entry": "Aug 15, 2019", "first_entry_pos": "38", "total_weeks": "4", "producers": "Charlie Puth, Johan Carlsson", "songwriters": "Jacob Kasher Hindlin, Charlie Puth, Johan Carlsson, Katy Perry", "source": "Capitol Records"}, {"week": "2019-09-05", "rank": 183, "song": "Paradise", "artist": "Bazzi", "streams": "4,725,386", "peak": "33", "previous": "170", "streak": "22", "release_date": "Aug 9, 2019", "first_entry": "Apr 11, 2019", "first_entry_pos": "83", "total_weeks": "22", "producers": "Bazzi, Kevin White", "songwriters": "Bazzi", "source": "iamcosmic"}, {"week": "2019-09-05", "rank": 184, "song": "Havana (feat. Young Thug)", "artist": "Camila Cabello, Young Thug", "streams": "4,712,477", "peak": "1", "previous": "173", "streak": "109", "release_date": "Jan 12, 2018", "first_entry": "Aug 10, 2017", "first_entry_pos": "87", "total_weeks": "109", "producers": "Frank Dukes", "songwriters": "Adam Feeney, Ali Tamposi, Andrew Watt, Brian Lee, Brittany Hazzard, Louis Bell, Pharrell Williams, Young Thug, Andrew Wotman, Camila Cabello, Kaan Gunesberk", "source": "Syco Music/Epic"}, {"week": "2019-09-05", "rank": 185, "song": "Juice", "artist": "Lizzo", "streams": "4,703,247", "peak": "155", "previous": "180", "streak": "2", "release_date": "Apr 19, 2019", "first_entry": "May 2, 2019", "first_entry_pos": "173", "total_weeks": "10", "producers": "Nate Mercereau, Ricky Reed", "songwriters": "Eric Frederic, Sam Sumser, Sean Small, Theron Thomas, Melissa Jefferson", "source": "Nice Life/Atlantic"}, {"week": "2019-09-05", "rank": 186, "song": "wish you were gay", "artist": "Billie Eilish", "streams": "4,694,589", "peak": "3", "previous": "176", "streak": "27", "release_date": "Mar 29, 2019", "first_entry": "Mar 7, 2019", "first_entry_pos": "50", "total_weeks": "27", "producers": "Finneas O'Connell", "songwriters": "Finneas O'Connell, Billie Eilish O'Connell", "source": "Darkroom/Interscope Records"}, {"week": "2019-09-05", "rank": 187, "song": "I Like It", "artist": "Cardi B, Bad Bunny, J Balvin", "streams": "4,680,791", "peak": "2", "previous": "174", "streak": "74", "release_date": "Apr 6, 2018", "first_entry": "Apr 12, 2018", "first_entry_pos": "26", "total_weeks": "74", "producers": "Craig Kallman, J. White Did It, Tainy", "songwriters": "Luian Malav\u00e9, Tainy, ANTHONY GERMAINE WHITE, Belcalis Almanzar, Benito Antonio Mart\u00ednez Ocasio, Benny Bonilla, Edgar Machuca, Edgar Wilmer Semper Vargas, Jordan Thorpe, Jose Alvaro Balvin Osorio, Manny Rodriguez, Marcos E. Masis, Noah Assad, Tony Pabon, Vincent Watson, Xavier Semer Vargas", "source": "Atlantic/KSR"}, {"week": "2019-09-05", "rank": 188, "song": "God's Plan", "artist": "Drake", "streams": "4,664,145", "peak": "1", "previous": "183", "streak": "85", "release_date": "Jun 29, 2018", "first_entry": "Jan 25, 2018", "first_entry_pos": "1", "total_weeks": "85", "producers": "Cardo Got Wings, Yung Exclusive, Boi-1da", "songwriters": "Matthew Samuels, Ronald LaTour, A. Graham, Brock Korsan, Daveon Jackson, Noah \"40\" Shebib", "source": "Cash Money/Drake LP6"}, {"week": "2019-09-05", "rank": 189, "song": "Psycho (feat. Ty Dolla $ign)", "artist": "Post Malone, Ty Dolla $ign", "streams": "4,654,794", "peak": "2", "previous": "\u2014", "streak": "1", "release_date": "Apr 27, 2018", "first_entry": "Mar 1, 2018", "first_entry_pos": "2", "total_weeks": "79", "producers": "Louis Bell, Post Malone", "songwriters": "Louis Bell, Austin Post, Carl Austin Rosen, Tyrone Griffin, Jr.", "source": "Republic Records"}, {"week": "2019-09-05", "rank": 190, "song": "F.N", "artist": "Lil Tjay", "streams": "4,643,346", "peak": "191", "previous": "\u2014", "streak": "1", "release_date": "Oct 11, 2019", "first_entry": "Sep 5, 2019", "first_entry_pos": "191", "total_weeks": "1", "producers": "MB13 Beatz", "songwriters": "Artem Romanov, Lil Tjay, Matthew Amis Bell", "source": "Columbia"}, {"week": "2019-09-05", "rank": 191, "song": "The greatest", "artist": "Lana Del Rey", "streams": "4,637,597", "peak": "192", "previous": "\u2014", "streak": "1", "release_date": "Aug 30, 2019", "first_entry": "Sep 5, 2019", "first_entry_pos": "192", "total_weeks": "1", "producers": "Lana Del Rey, Jack Antonoff", "songwriters": "Jack Antonoff, Lana Del Rey", "source": "Polydor Records"}, {"week": "2019-09-05", "rank": 192, "song": "i love you", "artist": "Billie Eilish", "streams": "4,623,615", "peak": "21", "previous": "178", "streak": "23", "release_date": "Mar 29, 2019", "first_entry": "Apr 4, 2019", "first_entry_pos": "21", "total_weeks": "23", "producers": "Finneas O'Connell", "songwriters": "Finneas O'Connell, Billie Eilish O'Connell", "source": "Darkroom/Interscope Records"}, {"week": "2019-09-05", "rank": 193, "song": "Jocelyn Flores", "artist": "XXXTENTACION", "streams": "4,598,347", "peak": "7", "previous": "187", "streak": "106", "release_date": "Aug 25, 2017", "first_entry": "Aug 31, 2017", "first_entry_pos": "25", "total_weeks": "106", "producers": "", "songwriters": "", "source": "Bad Vibes Forever / EMPIRE"}, {"week": "2019-09-05", "rank": 194, "song": "Something Just Like This", "artist": "The Chainsmokers, Coldplay", "streams": "4,570,687", "peak": "2", "previous": "179", "streak": "15", "release_date": "Apr 7, 2017", "first_entry": "Feb 23, 2017", "first_entry_pos": "132", "total_weeks": "115", "producers": "The Chainsmokers", "songwriters": "Andrew Taggart, Christopher Martin, Guy Berryman, Jonny Buckland, Will Champion", "source": "Disruptor Records/Columbia"}, {"week": "2019-09-05", "rank": 195, "song": "Pure Water (with Migos)", "artist": "Mustard, Migos", "streams": "4,554,360", "peak": "38", "previous": "189", "streak": "33", "release_date": "Jun 28, 2019", "first_entry": "Jan 24, 2019", "first_entry_pos": "162", "total_weeks": "33", "producers": "Mustard, GYLTTRYP", "songwriters": "Dijon McFarlane, Kiari Kendrell Cephus, Kirsnick Khari Ball, Quavious Keyate Marshall, Shah Rukh Zaman Khan", "source": "10 Summers Records/Interscope Records"}, {"week": "2019-09-05", "rank": 196, "song": "Congratulations", "artist": "Post Malone, Quavo", "streams": "4,543,995", "peak": "20", "previous": "\u2014", "streak": "1", "release_date": "Dec 9, 2016", "first_entry": "Jan 26, 2017", "first_entry_pos": "196", "total_weeks": "127", "producers": "Frank Dukes, Metro Boomin", "songwriters": "Adam Feeney, Louis Bell, Austin Post, Carl Rosen, Leland Wayne, Quavious Keyate Marshall", "source": "Universal Records"}, {"week": "2019-09-05", "rank": 197, "song": "False God", "artist": "Taylor Swift", "streams": "4,530,179", "peak": "52", "previous": "52", "streak": "2", "release_date": "Aug 23, 2019", "first_entry": "Aug 29, 2019", "first_entry_pos": "52", "total_weeks": "2", "producers": "Jack Antonoff, Taylor Swift", "songwriters": "Jack Antonoff, Taylor Swift", "source": "Taylor Swift"}, {"week": "2019-09-05", "rank": 198, "song": "California", "artist": "Lana Del Rey", "streams": "4,524,332", "peak": "199", "previous": "\u2014", "streak": "1", "release_date": "Aug 30, 2019", "first_entry": "Sep 5, 2019", "first_entry_pos": "199", "total_weeks": "1", "producers": "Zachary Dawes", "songwriters": "Lana Del Rey, Zachary Edwin Dawes", "source": "Polydor Records"}, {"week": "2019-09-05", "rank": 199, "song": "Wonderwall - Remastered", "artist": "Oasis", "streams": "4,517,948", "peak": "152", "previous": "186", "streak": "12", "release_date": "Aug 30, 2019", "first_entry": "Sep 5, 2019", "first_entry_pos": "199", "total_weeks": "1", "producers": "Zachary Dawes", "songwriters": "Lana Del Rey, Zachary Edwin Dawes", "source": "Polydor Records"}]